{
    "Blocks": {
        ".__BlockDct__": true,
        "Block-1": {
            ".__BlockDict__": true,
            "BlockDisplayName": "Dhw",
            "BlockName": "StorageTank",
            "__version__": "35f8800b-3a22-4080-acc2-13f332a84d50",
            "directPortPairs": [
                {
                    "__version__": "67aaee05-7d09-40e1-a6e2-d367c7196832",
                    "portPair": {
                        "__version__": "ed17e7a7-4798-4a80-beb7-81730523cf35",
                        "inputPort": {
                            "id": 19,
                            "relativeHeight": 0.01
                        },
                        "outputPort": {
                            "id": 20,
                            "relativeHeight": 0.99
                        },
                        "side": "right",
                        "trnsysId": 186
                    }
                }
            ],
            "heatExchangers": [
                {
                    "__version__": "2a5d6090-3ef5-4959-bba4-332654f007ac",
                    "id": 24,
                    "name": "TesHx24",
                    "portPair": {
                        "__version__": "ed17e7a7-4798-4a80-beb7-81730523cf35",
                        "inputPort": {
                            "id": 25,
                            "relativeHeight": 0.4
                        },
                        "outputPort": {
                            "id": 26,
                            "relativeHeight": 0.13
                        },
                        "side": "left",
                        "trnsysId": 185
                    },
                    "width": 40
                }
            ],
            "height": 220,
            "isHorizontallyFlipped": false,
            "isVerticallyFlipped": false,
            "position": [
                -540.0,
                -300.0
            ],
            "trnsysId": 7
        },
        "Block-2": {
            ".__BlockDict__": true,
            "BlockDisplayName": "SplitDhw",
            "BlockName": "TeePiece",
            "__version__": "d8a12235-c3f9-4742-bb7b-2c92a26d66c5",
            "teePieceModel": {
                "__version__": "260c8083-5343-4345-8cb3-0cdd374bc076",
                "blockItemModel": {
                    "__version__": "7b792574-5fa6-4c3e-b2e3-7e4eb71d7746",
                    "blockPosition": [
                        -220.0,
                        -320.0
                    ],
                    "flippedH": false,
                    "flippedV": false,
                    "rotationN": 0,
                    "trnsysId": 187
                },
                "inputPortId": 537,
                "outputPortIds": [
                    538,
                    539
                ]
            }
        },
        "Block-3": {
            ".__BlockDict__": true,
            "BlockDisplayName": "WTap2",
            "BlockName": "WTap",
            "__version__": "14afd9a0-54d6-44c7-b147-c79af3b782bb",
            "blockItemWithPrescribedMassFlow": {
                "__version__": "e9fd1a0e-c00a-46e2-abfb-7381fa1b2e2d",
                "blockItem": {
                    "__version__": "7b792574-5fa6-4c3e-b2e3-7e4eb71d7746",
                    "blockPosition": [
                        -189.0,
                        -385.0
                    ],
                    "flippedH": false,
                    "flippedV": false,
                    "rotationN": 0,
                    "trnsysId": 190
                },
                "massFlowRateInKgPerH": 700.0
            },
            "portId": 543
        },
        "Block-4": {
            ".__BlockDict__": true,
            "BlockDisplayName": "TeePiece",
            "BlockName": "TeePiece",
            "__version__": "d8a12235-c3f9-4742-bb7b-2c92a26d66c5",
            "teePieceModel": {
                "__version__": "260c8083-5343-4345-8cb3-0cdd374bc076",
                "blockItemModel": {
                    "__version__": "7b792574-5fa6-4c3e-b2e3-7e4eb71d7746",
                    "blockPosition": [
                        -320.0,
                        -102.0
                    ],
                    "flippedH": false,
                    "flippedV": false,
                    "rotationN": 0,
                    "trnsysId": 11
                },
                "inputPortId": 31,
                "outputPortIds": [
                    32,
                    33
                ]
            }
        },
        "Block-5": {
            ".__BlockDict__": true,
            "BlockDisplayName": "WTap_main",
            "BlockName": "WTap_main",
            "__version__": "14afd9a0-54d6-44c7-b147-c79af3b782bb",
            "blockItemWithPrescribedMassFlow": {
                "__version__": "e9fd1a0e-c00a-46e2-abfb-7381fa1b2e2d",
                "blockItem": {
                    "__version__": "7b792574-5fa6-4c3e-b2e3-7e4eb71d7746",
                    "blockPosition": [
                        -200.0,
                        -102.0
                    ],
                    "flippedH": false,
                    "flippedV": false,
                    "rotationN": 0,
                    "trnsysId": 12
                },
                "massFlowRateInKgPerH": 1000.0
            },
            "portId": 35
        },
        "Block-6": {
            ".__BlockDict__": true,
            "BlockDisplayName": "PuCol",
            "BlockName": "Pump",
            "__version__": "3d1e7f06-c7a6-49af-98b8-f593b34c5754",
            "blockItemWithPrescribedMassFlow": {
                "__version__": "e9fd1a0e-c00a-46e2-abfb-7381fa1b2e2d",
                "blockItem": {
                    "__version__": "7b792574-5fa6-4c3e-b2e3-7e4eb71d7746",
                    "blockPosition": [
                        -639.0,
                        -88.0
                    ],
                    "flippedH": false,
                    "flippedV": false,
                    "rotationN": 2,
                    "trnsysId": 15
                },
                "massFlowRateInKgPerH": 1000.0
            },
            "inputPortId": 43,
            "outputPortId": 44
        },
        "Block-7": {
            ".__BlockDict__": true,
            "BlockDisplayName": "Collector",
            "BlockName": "Collector",
            "__version__": "e8cfde2f-8239-4338-a5f0-63a7abb93900",
            "blockPosition": [
                -879.0,
                -208.0
            ],
            "flippedH": false,
            "flippedV": false,
            "portsIdsIn": [
                46
            ],
            "portsIdsOut": [
                47
            ],
            "rotationN": 0,
            "trnsysId": 16
        },
        "Block-8": {
            ".__BlockDict__": true,
            "BlockDisplayName": "MixDhw",
            "BlockName": "TVentil",
            "IsTempering": true,
            "PositionForMassFlowSolver": "1.0",
            "__version__": "ccf7f590-c65e-4fa1-bf7c-1850a5f8985e",
            "blockItemModel": {
                "__version__": "7b792574-5fa6-4c3e-b2e3-7e4eb71d7746",
                "blockPosition": [
                    -320.0,
                    -318.0
                ],
                "flippedH": false,
                "flippedV": true,
                "rotationN": 0,
                "trnsysId": 84
            },
            "inputPortId": 252,
            "outputPortIds": [
                250,
                251
            ]
        },
        "Block-9": {
            ".__BlockDict__": true,
            "BlockDisplayName": "WTap",
            "BlockName": "WTap",
            "__version__": "14afd9a0-54d6-44c7-b147-c79af3b782bb",
            "blockItemWithPrescribedMassFlow": {
                "__version__": "e9fd1a0e-c00a-46e2-abfb-7381fa1b2e2d",
                "blockItem": {
                    "__version__": "7b792574-5fa6-4c3e-b2e3-7e4eb71d7746",
                    "blockPosition": [
                        -100.0,
                        -320.0
                    ],
                    "flippedH": false,
                    "flippedV": false,
                    "rotationN": 0,
                    "trnsysId": 87
                },
                "massFlowRateInKgPerH": 300.0
            },
            "portId": 260
        },
        "Connection-10": {
            ".__ConnectionDict__": true,
            "__version__": "74032e79-2abc-4fcf-9328-5d697ef31023",
            "connectionId": 74,
            "diameterInCm": {
                "name": "loop4Dia"
            },
            "fromPortId": 20,
            "id": 322,
            "labelPos": [
                -330.0,
                -227.8
            ],
            "lengthInM": {
                "name": "loop4Len"
            },
            "massFlowLabelPos": [
                -556.0,
                -341.79999999999995
            ],
            "name": "PiTesDhwOut",
            "segmentsCorners": [
                [
                    -370.0,
                    -297.8
                ],
                [
                    -370.0,
                    -297.0
                ],
                [
                    -339.0,
                    -297.0
                ],
                [
                    -339.0,
                    -298.0
                ]
            ],
            "shallBeSimulated": true,
            "toPortId": 250,
            "trnsysId": 109,
            "uValueInWPerM2K": {
                "name": "loop4UVal"
            }
        },
        "Connection-11": {
            ".__ConnectionDict__": true,
            "__version__": "74032e79-2abc-4fcf-9328-5d697ef31023",
            "connectionId": 79,
            "diameterInCm": {
                "name": "loop2Dia"
            },
            "fromPortId": 44,
            "id": 337,
            "labelPos": [
                -669.0,
                -38.0
            ],
            "lengthInM": {
                "name": "loop2Len"
            },
            "massFlowLabelPos": [
                -810.0,
                -45.0
            ],
            "name": "PiColIn",
            "segmentsCorners": [
                [
                    -719.0,
                    -108.0
                ],
                [
                    -719.0,
                    -108.0
                ]
            ],
            "shallBeSimulated": true,
            "toPortId": 46,
            "trnsysId": 114,
            "uValueInWPerM2K": {
                "name": "loop2UVal"
            }
        },
        "Connection-12": {
            ".__ConnectionDict__": true,
            "__version__": "74032e79-2abc-4fcf-9328-5d697ef31023",
            "connectionId": 91,
            "diameterInCm": {
                "name": "loop2Dia"
            },
            "fromPortId": 47,
            "id": 381,
            "labelPos": [
                -689.0,
                -138.0
            ],
            "lengthInM": {
                "name": "loop2Len"
            },
            "massFlowLabelPos": [
                -716.0,
                -223.0
            ],
            "name": "PiColOut",
            "segmentsCorners": [
                [
                    -653.5,
                    -188.0
                ],
                [
                    -653.5,
                    -169.0
                ],
                [
                    -614.0,
                    -169.0
                ],
                [
                    -614.0,
                    -168.0
                ]
            ],
            "shallBeSimulated": true,
            "toPortId": 25,
            "trnsysId": 130,
            "uValueInWPerM2K": {
                "name": "loop2UVal"
            }
        },
        "Connection-13": {
            ".__ConnectionDict__": true,
            "__version__": "74032e79-2abc-4fcf-9328-5d697ef31023",
            "connectionId": 97,
            "diameterInCm": {
                "name": "loop4Dia"
            },
            "fromPortId": 35,
            "id": 403,
            "labelPos": [
                -210.0,
                -32.0
            ],
            "lengthInM": {
                "name": "loop4Len"
            },
            "massFlowLabelPos": [
                -267.0,
                -67.0
            ],
            "name": "PiDhwMains",
            "segmentsCorners": [
                [
                    -240.0,
                    -82.0
                ],
                [
                    -240.0,
                    -82.0
                ]
            ],
            "shallBeSimulated": true,
            "toPortId": 32,
            "trnsysId": 138,
            "uValueInWPerM2K": {
                "name": "loop4UVal"
            }
        },
        "Connection-14": {
            ".__ConnectionDict__": true,
            "__version__": "74032e79-2abc-4fcf-9328-5d697ef31023",
            "connectionId": 154,
            "diameterInCm": {
                "name": "loop4Dia"
            },
            "fromPortId": 539,
            "id": 566,
            "labelPos": [
                -204.0,
                -323.0
            ],
            "lengthInM": {
                "name": "loop4Len"
            },
            "massFlowLabelPos": [
                -204.0,
                -323.0
            ],
            "name": "Tee536_WTap2",
            "segmentsCorners": [
                [
                    -200.0,
                    -365.0
                ]
            ],
            "shallBeSimulated": true,
            "toPortId": 543,
            "trnsysId": 213,
            "uValueInWPerM2K": {
                "name": "loop4UVal"
            }
        },
        "Connection-15": {
            ".__ConnectionDict__": true,
            "__version__": "74032e79-2abc-4fcf-9328-5d697ef31023",
            "connectionId": 155,
            "diameterInCm": {
                "name": "loop4Dia"
            },
            "fromPortId": 538,
            "id": 567,
            "labelPos": [
                -184.0,
                -303.0
            ],
            "lengthInM": {
                "name": "loop4Len"
            },
            "massFlowLabelPos": [
                -184.0,
                -303.0
            ],
            "name": "Tee536_WTap",
            "segmentsCorners": [
                [
                    -141.0,
                    -300.0
                ],
                [
                    -141.0,
                    -300.0
                ]
            ],
            "shallBeSimulated": true,
            "toPortId": 260,
            "trnsysId": 214,
            "uValueInWPerM2K": {
                "name": "loop4UVal"
            }
        },
        "Connection-16": {
            ".__ConnectionDict__": true,
            "__version__": "74032e79-2abc-4fcf-9328-5d697ef31023",
            "connectionId": 163,
            "diameterInCm": {
                "name": "loop2Dia"
            },
            "fromPortId": 26,
            "id": 575,
            "labelPos": [
                -551.0,
                -121.0
            ],
            "lengthInM": {
                "name": "loop2Len"
            },
            "massFlowLabelPos": [
                -551.0,
                -121.0
            ],
            "name": "Dhw_PuCol",
            "segmentsCorners": [
                [
                    -593.5,
                    -118.0
                ],
                [
                    -593.5,
                    -108.0
                ]
            ],
            "shallBeSimulated": true,
            "toPortId": 43,
            "trnsysId": 222,
            "uValueInWPerM2K": {
                "name": "loop2UVal"
            }
        },
        "Connection-17": {
            ".__ConnectionDict__": true,
            "__version__": "74032e79-2abc-4fcf-9328-5d697ef31023",
            "connectionId": 172,
            "diameterInCm": {
                "name": "loop4Dia"
            },
            "fromPortId": 252,
            "id": 584,
            "labelPos": [
                -283.0,
                -301.0
            ],
            "lengthInM": {
                "name": "loop4Len"
            },
            "massFlowLabelPos": [
                -283.0,
                -301.0
            ],
            "name": "MixDhw_SplitDhw",
            "segmentsCorners": [
                [
                    -251.5,
                    -298.0
                ],
                [
                    -251.5,
                    -300.0
                ]
            ],
            "shallBeSimulated": true,
            "toPortId": 537,
            "trnsysId": 231,
            "uValueInWPerM2K": {
                "name": "loop4UVal"
            }
        },
        "Connection-18": {
            ".__ConnectionDict__": true,
            "__version__": "74032e79-2abc-4fcf-9328-5d697ef31023",
            "connectionId": 57,
            "diameterInCm": {
                "name": "loop4Dia"
            },
            "fromPortId": 33,
            "id": 267,
            "labelPos": [
                -210.0,
                -32.0
            ],
            "lengthInM": {
                "name": "loop4Len"
            },
            "massFlowLabelPos": [
                -289.0,
                -192.0
            ],
            "name": "PiCirc",
            "segmentsCorners": [
                [
                    -300.0,
                    -278.0
                ]
            ],
            "shallBeSimulated": true,
            "toPortId": 251,
            "trnsysId": 90,
            "uValueInWPerM2K": {
                "name": "loop4UVal"
            }
        },
        "Connection-19": {
            ".__ConnectionDict__": true,
            "__version__": "74032e79-2abc-4fcf-9328-5d697ef31023",
            "connectionId": 72,
            "diameterInCm": {
                "name": "loop4Dia"
            },
            "fromPortId": 31,
            "id": 316,
            "labelPos": [
                -310.0,
                -12.0
            ],
            "lengthInM": {
                "name": "loop4Len"
            },
            "massFlowLabelPos": [
                -469.0,
                -67.0
            ],
            "name": "PiTesDhwIn",
            "segmentsCorners": [
                [
                    -359.0,
                    -82.0
                ],
                [
                    -382.0,
                    -82.0
                ],
                [
                    -382.0,
                    -82.19999999999999
                ]
            ],
            "shallBeSimulated": true,
            "toPortId": 19,
            "trnsysId": 107,
            "uValueInWPerM2K": {
                "name": "loop4UVal"
            }
        },
        "IDs": {
            "GlobalId": 605,
            "__idDct__": true,
            "globalConnID": 181,
            "trnsysID": 242
        },
        "Strings": {
            "DiagramName": "solar_dhw_GUI.json",
            "ProjectFolder": "C:\\Users\\damian.birchler\\src\\pytrnsys\\wd2\\pytrnsys_gui\\data\\examples\\solar_dhw_GUI",
            "__nameDct__": true
        }
    },
    "hydraulicLoops": [
        {
            "__version__": "990b8023-eb4b-408e-8d54-23caa5916b2a",
            "connectionsTrnsysId": [
                114,
                130,
                222
            ],
            "fluidName": "brine",
            "hasUserDefinedName": false,
            "name": "loop2",
            "useLoopWideDefaults": true
        },
        {
            "__version__": "990b8023-eb4b-408e-8d54-23caa5916b2a",
            "connectionsTrnsysId": [
                231,
                90,
                138,
                107,
                109,
                214,
                213
            ],
            "fluidName": "water",
            "hasUserDefinedName": false,
            "name": "loop4",
            "useLoopWideDefaults": true
        }
    ]
}