{
    "Blocks": {
        "..__GroupDct-CircnLoop": {
            ".__GroupDict__": true,
            "GroupName": "CircnLoop",
            "Position": [
                -595.0,
                -336.0
            ],
            "Size": [
                744.0,
                525.0
            ]
        },
        "..__GroupDct-ShLoop": {
            ".__GroupDict__": true,
            "GroupName": "ShLoop",
            "Position": [
                -344.0,
                -323.0
            ],
            "Size": [
                750.0,
                558.0
            ]
        },
        "..__GroupDct-defaultGroup": {
            ".__GroupDict__": true,
            "GroupName": "defaultGroup",
            "Position": [
                0,
                0
            ],
            "Size": [
                100,
                100
            ]
        },
        ".__BlockDct__": true,
        "Block-123": {
            ".__BlockDict__": true,
            "BlockDisplayName": "IceStorage123",
            "BlockName": "IceStorage",
            "BlockPosition": [
                -1333.0,
                27.0
            ],
            "FlippedH": false,
            "FlippedV": false,
            "GroupName": "defaultGroup",
            "ID": 123,
            "PortsIDIn": [
                124
            ],
            "PortsIDOut": [
                125
            ],
            "RotationN": 0,
            "trnsysID": 37
        },
        "Block-126": {
            ".__BlockDict__": true,
            "BlockDisplayName": "TeeOutIce",
            "BlockName": "TeePiece",
            "BlockPosition": [
                -1146.0,
                -187.0
            ],
            "FlippedH": false,
            "FlippedV": false,
            "GroupName": "defaultGroup",
            "ID": 126,
            "PortsIDIn": [
                127,
                128
            ],
            "PortsIDOut": [
                129
            ],
            "RotationN": 1,
            "trnsysID": 38
        },
        "Block-130": {
            ".__BlockDict__": true,
            "BlockDisplayName": "TeeColToHp",
            "BlockName": "TeePiece",
            "BlockPosition": [
                -1161.0,
                -313.0
            ],
            "FlippedH": false,
            "FlippedV": false,
            "GroupName": "defaultGroup",
            "ID": 130,
            "PortsIDIn": [
                131,
                132
            ],
            "PortsIDOut": [
                133
            ],
            "RotationN": 1,
            "trnsysID": 39
        },
        "Block-134": {
            ".__BlockDict__": true,
            "BlockDisplayName": "DivHpEvap",
            "BlockName": "TVentil",
            "BlockPosition": [
                -1044.0,
                -311.0
            ],
            "FlippedH": false,
            "FlippedV": true,
            "GroupName": "defaultGroup",
            "ID": 134,
            "IsTempering": true,
            "PortsIDIn": [
                135,
                136
            ],
            "PortsIDOut": [
                137
            ],
            "PositionForMassFlowSolver": 1.0,
            "RotationN": 0,
            "trnsysID": 40
        },
        "Block-138": {
            ".__BlockDict__": true,
            "BlockDisplayName": "TeeHpEvap",
            "BlockName": "TeePiece",
            "BlockPosition": [
                -1044.0,
                -215.0
            ],
            "FlippedH": false,
            "FlippedV": false,
            "GroupName": "defaultGroup",
            "ID": 138,
            "PortsIDIn": [
                139,
                140
            ],
            "PortsIDOut": [
                141
            ],
            "RotationN": 0,
            "trnsysID": 41
        },
        "Block-1617": {
            ".__BlockDict__": true,
            "BlockDisplayName": "PuHpCond",
            "BlockName": "Pump",
            "BlockPosition": [
                -841.0,
                -169.0
            ],
            "FlippedH": false,
            "FlippedV": false,
            "GroupName": "defaultGroup",
            "ID": 1617,
            "PortsIDIn": [
                1618
            ],
            "PortsIDOut": [
                1619
            ],
            "RotationN": -1,
            "trnsysID": 522
        },
        "Block-166": {
            ".__BlockDict__": true,
            "BlockDisplayName": "HP",
            "BlockName": "HP",
            "FlippedH": false,
            "FlippedV": false,
            "GroupName": "defaultGroup",
            "HeatPumpPosition": [
                -938.0,
                -298.0
            ],
            "ID": 166,
            "PortsIDIn": [
                167,
                168
            ],
            "PortsIDOut": [
                169,
                170
            ],
            "RotationN": 0,
            "childIds": [
                48,
                49
            ],
            "trnsysID": 48
        },
        "Block-171": {
            ".__BlockDict__": true,
            "BlockDisplayName": "DivHp",
            "BlockName": "TVentil",
            "BlockPosition": [
                -858.0,
                -437.0
            ],
            "FlippedH": false,
            "FlippedV": false,
            "GroupName": "defaultGroup",
            "ID": 171,
            "IsTempering": false,
            "PortsIDIn": [
                172,
                173
            ],
            "PortsIDOut": [
                174
            ],
            "PositionForMassFlowSolver": 1.0,
            "RotationN": 1,
            "trnsysID": 50
        },
        "Block-175": {
            ".__BlockDict__": true,
            "BlockDisplayName": "HxCool",
            "BlockName": "ExternalHx",
            "ExternalHxPosition": [
                -638.0,
                51.0
            ],
            "FlippedH": false,
            "FlippedV": false,
            "GroupName": "defaultGroup",
            "ID": 175,
            "PortsIDIn": [
                176,
                177
            ],
            "PortsIDOut": [
                178,
                179
            ],
            "RotationN": 0,
            "childIds": [
                51,
                52
            ],
            "trnsysID": 51
        },
        "Block-180": {
            ".__BlockDict__": true,
            "BlockDisplayName": "PuCool",
            "BlockName": "Pump",
            "BlockPosition": [
                -800.0,
                56.0
            ],
            "FlippedH": false,
            "FlippedV": false,
            "GroupName": "defaultGroup",
            "ID": 180,
            "PortsIDIn": [
                181
            ],
            "PortsIDOut": [
                182
            ],
            "RotationN": 0,
            "trnsysID": 53
        },
        "Block-183": {
            ".__BlockDict__": true,
            "BlockDisplayName": "DivSHCool",
            "BlockName": "TVentil",
            "BlockPosition": [
                -507.0,
                -68.0
            ],
            "FlippedH": false,
            "FlippedV": true,
            "GroupName": "CircnLoop",
            "ID": 183,
            "IsTempering": false,
            "PortsIDIn": [
                184,
                185
            ],
            "PortsIDOut": [
                186
            ],
            "PositionForMassFlowSolver": 1.0,
            "RotationN": 0,
            "trnsysID": 54
        },
        "Block-187": {
            ".__BlockDict__": true,
            "BlockDisplayName": "TeeCoolRadIn",
            "BlockName": "TeePiece",
            "BlockPosition": [
                -533.0,
                -224.0
            ],
            "FlippedH": false,
            "FlippedV": false,
            "GroupName": "CircnLoop",
            "ID": 187,
            "PortsIDIn": [
                188,
                189
            ],
            "PortsIDOut": [
                190
            ],
            "RotationN": 1,
            "trnsysID": 55
        },
        "Block-195": {
            ".__BlockDict__": true,
            "BlockDisplayName": "TeeDivTes",
            "BlockName": "TeePiece",
            "BlockPosition": [
                -1150.0,
                -652.0
            ],
            "FlippedH": false,
            "FlippedV": true,
            "GroupName": "defaultGroup",
            "ID": 195,
            "PortsIDIn": [
                196,
                197
            ],
            "PortsIDOut": [
                198
            ],
            "RotationN": 0,
            "trnsysID": 57
        },
        "Block-1975": {
            ".__BlockDict__": true,
            "BlockDisplayName": "Dhw",
            "BlockName": "StorageTank",
            "FlippedH": false,
            "FlippedV": false,
            "GroupName": "defaultGroup",
            "HxList": [
                {
                    "DisplayName": "Solar1976",
                    "Height": 40.0,
                    "ID": 1976,
                    "Offset": [
                        0.0,
                        154.0
                    ],
                    "ParentID": 1975,
                    "Port1ID": 1977,
                    "Port2ID": 1978,
                    "SideNr": 0,
                    "Width": 40,
                    "connTrnsysID": 639
                }
            ],
            "ID": 1975,
            "PortPairList": [
                {
                    "ConnCID": 440,
                    "ConnDisName": "UntitledConn440",
                    "ConnID": 1984,
                    "Port1ID": 1982,
                    "Port1offset": 11.0,
                    "Port2ID": 1983,
                    "Port2offset": 209.0,
                    "Side": true,
                    "trnsysID": 641
                },
                {
                    "ConnCID": 441,
                    "ConnDisName": "UntitledConn441",
                    "ConnID": 1989,
                    "Port1ID": 1987,
                    "Port1offset": 11.0,
                    "Port2ID": 1988,
                    "Port2offset": 209.0,
                    "Side": false,
                    "trnsysID": 643
                },
                {
                    "ConnCID": 442,
                    "ConnDisName": "UntitledConn442",
                    "ConnID": 1994,
                    "Port1ID": 1992,
                    "Port1offset": 22.0,
                    "Port2ID": 1993,
                    "Port2offset": 66.0,
                    "Side": false,
                    "trnsysID": 645
                }
            ],
            "StoragePosition": [
                -716.0,
                -673.0
            ],
            "size_h": 220.0,
            "trnsysID": 638
        },
        "Block-199": {
            ".__BlockDict__": true,
            "BlockDisplayName": "MixHxTes",
            "BlockName": "TVentil",
            "BlockPosition": [
                -1006.0,
                -565.0
            ],
            "FlippedH": true,
            "FlippedV": true,
            "GroupName": "defaultGroup",
            "ID": 199,
            "IsTempering": false,
            "PortsIDIn": [
                200,
                201
            ],
            "PortsIDOut": [
                202
            ],
            "PositionForMassFlowSolver": 1.0,
            "RotationN": 0,
            "trnsysID": 58
        },
        "Block-2026": {
            ".__BlockDict__": true,
            "BlockDisplayName": "SH",
            "BlockName": "StorageTank",
            "FlippedH": false,
            "FlippedV": false,
            "GroupName": "defaultGroup",
            "HxList": [
                {
                    "DisplayName": "SolarTesHx2279",
                    "Height": 40.0,
                    "ID": 2279,
                    "Offset": [
                        0.0,
                        154.0
                    ],
                    "ParentID": 2026,
                    "Port1ID": 2280,
                    "Port2ID": 2281,
                    "SideNr": 0,
                    "Width": 40,
                    "connTrnsysID": 738
                }
            ],
            "ID": 2026,
            "PortPairList": [
                {
                    "ConnCID": 452,
                    "ConnDisName": "UntitledConn452",
                    "ConnID": 2029,
                    "Port1ID": 2027,
                    "Port1offset": 11.0,
                    "Port2ID": 2028,
                    "Port2offset": 209.0,
                    "Side": true,
                    "trnsysID": 658
                },
                {
                    "ConnCID": 453,
                    "ConnDisName": "UntitledConn453",
                    "ConnID": 2034,
                    "Port1ID": 2032,
                    "Port1offset": 11.0,
                    "Port2ID": 2033,
                    "Port2offset": 209.0,
                    "Side": false,
                    "trnsysID": 660
                }
            ],
            "StoragePosition": [
                -708.0,
                -288.0
            ],
            "size_h": 220.0,
            "trnsysID": 656
        },
        "Block-203": {
            ".__BlockDict__": true,
            "BlockDisplayName": "PuCol",
            "BlockName": "Pump",
            "BlockPosition": [
                -1092.0,
                -557.0
            ],
            "FlippedH": true,
            "FlippedV": false,
            "GroupName": "defaultGroup",
            "ID": 203,
            "PortsIDIn": [
                204
            ],
            "PortsIDOut": [
                205
            ],
            "RotationN": 0,
            "trnsysID": 59
        },
        "Block-207": {
            ".__BlockDict__": true,
            "BlockDisplayName": "TeeCoolBriOut",
            "BlockName": "TeePiece",
            "BlockPosition": [
                -1058.0,
                100.0
            ],
            "FlippedH": false,
            "FlippedV": false,
            "GroupName": "defaultGroup",
            "ID": 207,
            "PortsIDIn": [
                208,
                209
            ],
            "PortsIDOut": [
                210
            ],
            "RotationN": 0,
            "trnsysID": 61
        },
        "Block-211": {
            ".__BlockDict__": true,
            "BlockDisplayName": "TeeCoolBriIn",
            "BlockName": "TeePiece",
            "BlockPosition": [
                -1149.0,
                2.0
            ],
            "FlippedH": false,
            "FlippedV": false,
            "GroupName": "defaultGroup",
            "ID": 211,
            "PortsIDIn": [
                212,
                213
            ],
            "PortsIDOut": [
                214
            ],
            "RotationN": 0,
            "trnsysID": 62
        },
        "Block-2294": {
            ".__BlockDict__": true,
            "BlockDisplayName": "DivSolarDhwSh",
            "BlockName": "TVentil",
            "BlockPosition": [
                -869.0,
                -512.0
            ],
            "FlippedH": true,
            "FlippedV": true,
            "GroupName": "defaultGroup",
            "ID": 2294,
            "IsTempering": false,
            "PortsIDIn": [
                2295,
                2296
            ],
            "PortsIDOut": [
                2297
            ],
            "PositionForMassFlowSolver": 1.0,
            "RotationN": 0,
            "trnsysID": 742
        },
        "Block-2319": {
            ".__BlockDict__": true,
            "BlockDisplayName": "TeeSolarDhwSh",
            "BlockName": "TeePiece",
            "BlockPosition": [
                -976.0,
                -653.0
            ],
            "FlippedH": false,
            "FlippedV": true,
            "GroupName": "defaultGroup",
            "ID": 2319,
            "PortsIDIn": [
                2320,
                2321
            ],
            "PortsIDOut": [
                2322
            ],
            "RotationN": 0,
            "trnsysID": 750
        },
        "Block-3065": {
            ".__BlockDict__": true,
            "BlockDisplayName": "DivDhw",
            "BlockName": "TVentil",
            "BlockPosition": [
                -468.0,
                -475.0
            ],
            "FlippedH": false,
            "FlippedV": false,
            "GroupName": "defaultGroup",
            "ID": 3065,
            "IsTempering": false,
            "PortsIDIn": [
                3066,
                3067
            ],
            "PortsIDOut": [
                3068
            ],
            "PositionForMassFlowSolver": null,
            "RotationN": 0,
            "trnsysID": 990
        },
        "Block-308": {
            ".__BlockDict__": true,
            "BlockDisplayName": "HxDHW",
            "BlockName": "ExternalHx",
            "ExternalHxPosition": [
                -231.0,
                -657.0
            ],
            "FlippedH": false,
            "FlippedV": false,
            "GroupName": "defaultGroup",
            "ID": 308,
            "PortsIDIn": [
                309,
                310
            ],
            "PortsIDOut": [
                311,
                312
            ],
            "RotationN": 0,
            "childIds": [
                94,
                95
            ],
            "trnsysID": 94
        },
        "Block-3081": {
            ".__BlockDict__": true,
            "BlockDisplayName": "TeePieceCirc2",
            "BlockName": "TeePiece",
            "BlockPosition": [
                -95.0,
                -457.0
            ],
            "FlippedH": false,
            "FlippedV": false,
            "GroupName": "defaultGroup",
            "ID": 3081,
            "PortsIDIn": [
                3082,
                3083
            ],
            "PortsIDOut": [
                3084
            ],
            "RotationN": 0,
            "trnsysID": 995
        },
        "Block-3088": {
            ".__BlockDict__": true,
            "BlockDisplayName": "TeePieceCirc1",
            "BlockName": "TeePiece",
            "BlockPosition": [
                -26.0,
                -691.0
            ],
            "FlippedH": false,
            "FlippedV": true,
            "GroupName": "defaultGroup",
            "ID": 3088,
            "PortsIDIn": [
                3089,
                3090
            ],
            "PortsIDOut": [
                3091
            ],
            "RotationN": 0,
            "trnsysID": 997
        },
        "Block-3107": {
            ".__BlockDict__": true,
            "BlockDisplayName": "TeePieceHpRt",
            "BlockName": "TeePiece",
            "BlockPosition": [
                -815.0,
                -111.0
            ],
            "FlippedH": false,
            "FlippedV": false,
            "GroupName": "defaultGroup",
            "ID": 3107,
            "PortsIDIn": [
                3108,
                3109
            ],
            "PortsIDOut": [
                3110
            ],
            "RotationN": 0,
            "trnsysID": 1003
        },
        "Block-322": {
            ".__BlockDict__": true,
            "BlockDisplayName": "PuDHW",
            "BlockName": "Pump",
            "BlockPosition": [
                -316.0,
                -462.0
            ],
            "FlippedH": true,
            "FlippedV": false,
            "GroupName": "defaultGroup",
            "ID": 322,
            "PortsIDIn": [
                323
            ],
            "PortsIDOut": [
                324
            ],
            "RotationN": 0,
            "trnsysID": 99
        },
        "Block-3261": {
            ".__BlockDict__": true,
            "BlockDisplayName": "DivDhwOut",
            "BlockName": "TVentil",
            "BlockPosition": [
                -495.0,
                -685.0
            ],
            "FlippedH": false,
            "FlippedV": true,
            "GroupName": "defaultGroup",
            "ID": 3261,
            "IsTempering": false,
            "PortsIDIn": [
                3262,
                3263
            ],
            "PortsIDOut": [
                3264
            ],
            "PositionForMassFlowSolver": null,
            "RotationN": 0,
            "trnsysID": 1053
        },
        "Block-331": {
            ".__BlockDict__": true,
            "BlockDisplayName": "PuCirc",
            "BlockName": "Pump",
            "BlockPosition": [
                -44.0,
                -524.0
            ],
            "FlippedH": true,
            "FlippedV": false,
            "GroupName": "defaultGroup",
            "ID": 331,
            "PortsIDIn": [
                332
            ],
            "PortsIDOut": [
                333
            ],
            "RotationN": 0,
            "trnsysID": 102
        },
        "Block-364": {
            ".__BlockDict__": true,
            "BlockDisplayName": "PuHpEvap",
            "BlockName": "Pump",
            "BlockPosition": [
                -969.0,
                -198.0
            ],
            "FlippedH": true,
            "FlippedV": false,
            "GroupName": "defaultGroup",
            "ID": 364,
            "PortsIDIn": [
                365
            ],
            "PortsIDOut": [
                366
            ],
            "RotationN": 0,
            "trnsysID": 113
        },
        "Block-48": {
            ".__BlockDict__": true,
            "BlockDisplayName": "Coll",
            "BlockName": "Kollektor",
            "BlockPosition": [
                -1319.0,
                -657.0
            ],
            "FlippedH": false,
            "FlippedV": false,
            "GroupName": "defaultGroup",
            "ID": 48,
            "PortsIDIn": [
                49
            ],
            "PortsIDOut": [
                50
            ],
            "RotationN": 0,
            "trnsysID": 14
        },
        "Block-51": {
            ".__BlockDict__": true,
            "BlockDisplayName": "RadiatorSH",
            "BlockName": "Radiator",
            "BlockPosition": [
                40.0,
                -188.0
            ],
            "FlippedH": false,
            "FlippedV": false,
            "GroupName": "CircnLoop",
            "ID": 51,
            "PortsIDIn": [
                52
            ],
            "PortsIDOut": [
                53
            ],
            "RotationN": 0,
            "trnsysID": 15
        },
        "Block-54": {
            ".__BlockDict__": true,
            "BlockDisplayName": "PuSH",
            "BlockName": "Pump",
            "BlockPosition": [
                -240.0,
                -202.0
            ],
            "FlippedH": false,
            "FlippedV": false,
            "GroupName": "CircnLoop",
            "ID": 54,
            "PortsIDIn": [
                55
            ],
            "PortsIDOut": [
                56
            ],
            "RotationN": 0,
            "trnsysID": 16
        },
        "Block-60": {
            ".__BlockDict__": true,
            "BlockDisplayName": "DivSH",
            "BlockName": "TVentil",
            "BlockPosition": [
                -257.0,
                -120.0
            ],
            "FlippedH": false,
            "FlippedV": false,
            "GroupName": "CircnLoop",
            "ID": 60,
            "IsTempering": true,
            "PortsIDIn": [
                61,
                62
            ],
            "PortsIDOut": [
                63
            ],
            "PositionForMassFlowSolver": 1.0,
            "RotationN": 0,
            "trnsysID": 18
        },
        "Block-67": {
            ".__BlockDict__": true,
            "BlockDisplayName": "TeeMixSH",
            "BlockName": "TeePiece",
            "BlockPosition": [
                -392.0,
                -190.0
            ],
            "FlippedH": false,
            "FlippedV": true,
            "GroupName": "CircnLoop",
            "ID": 67,
            "PortsIDIn": [
                68,
                69
            ],
            "PortsIDOut": [
                70
            ],
            "RotationN": 0,
            "trnsysID": 20
        },
        "Block-77": {
            ".__BlockDict__": true,
            "BlockDisplayName": "tapWater",
            "BlockName": "WTap",
            "BlockPosition": [
                86.0,
                -749.0
            ],
            "FlippedH": false,
            "FlippedV": false,
            "GroupName": "defaultGroup",
            "ID": 77,
            "PortsIDIn": [
                78
            ],
            "PortsIDOut": [],
            "RotationN": 0,
            "trnsysID": 23
        },
        "Block-79": {
            ".__BlockDict__": true,
            "BlockDisplayName": "supplyWater",
            "BlockName": "WTap_main",
            "BlockPosition": [
                74.0,
                -491.0
            ],
            "FlippedH": false,
            "FlippedV": false,
            "GroupName": "defaultGroup",
            "ID": 79,
            "PortsIDIn": [
                80
            ],
            "PortsIDOut": [],
            "RotationN": 0,
            "trnsysID": 24
        },
        "Connection-1623": {
            ".__ConnectionDict__": true,
            "ConnCID": 358,
            "ConnDisplayName": "PiHpCondIn",
            "ConnID": 1623,
            "CornerPositions": [
                [
                    -828.0,
                    -209.0
                ],
                [
                    -828.0,
                    -231.33333333333331
                ]
            ],
            "FirstSegmentLabelPos": [
                70.0,
                50.0
            ],
            "GroupName": "defaultGroup",
            "PortFromID": 1619,
            "PortToID": 170,
            "SegmentPositions": [
                [
                    -824.5,
                    -209.0,
                    -828.0,
                    -209.0
                ],
                [
                    -828.0,
                    -209.0,
                    -828.0,
                    -231.33333333333331
                ],
                [
                    -828.0,
                    -231.33333333333331,
                    -830.0,
                    -231.33333333333331
                ]
            ],
            "isVirtualConn": false,
            "trnsysID": 524
        },
        "Connection-2008": {
            ".__ConnectionDict__": true,
            "ConnCID": 446,
            "ConnDisplayName": "PiHpToTesDhwIn",
            "ConnID": 2008,
            "CornerPositions": [
                [
                    -886.3888888888889,
                    -445.0
                ],
                [
                    -886.3888888888889,
                    -662.0
                ]
            ],
            "FirstSegmentLabelPos": [
                70.0,
                50.0
            ],
            "GroupName": "defaultGroup",
            "PortFromID": 172,
            "PortToID": 1982,
            "SegmentPositions": [
                [
                    -885.7777777777778,
                    -445.0,
                    -886.3888888888889,
                    -445.0
                ],
                [
                    -886.3888888888889,
                    -445.0,
                    -886.3888888888889,
                    -662.0
                ],
                [
                    -886.3888888888889,
                    -662.0,
                    -724.0,
                    -662.0
                ]
            ],
            "isVirtualConn": false,
            "trnsysID": 650
        },
        "Connection-2042": {
            ".__ConnectionDict__": true,
            "ConnCID": 455,
            "ConnDisplayName": "PiHptoTesSHIn",
            "ConnID": 2042,
            "CornerPositions": [
                [
                    -809.0,
                    -412.0
                ],
                [
                    -809.0,
                    -277.0
                ]
            ],
            "FirstSegmentLabelPos": [
                70.0,
                50.0
            ],
            "GroupName": "defaultGroup",
            "PortFromID": 173,
            "PortToID": 2027,
            "SegmentPositions": [
                [
                    -850.0,
                    -412.0,
                    -809.0,
                    -412.0
                ],
                [
                    -809.0,
                    -412.0,
                    -809.0,
                    -277.0
                ],
                [
                    -809.0,
                    -277.0,
                    -716.0,
                    -277.0
                ]
            ],
            "isVirtualConn": false,
            "trnsysID": 663
        },
        "Connection-2048": {
            ".__ConnectionDict__": true,
            "ConnCID": 457,
            "ConnDisplayName": "PiTesDhwToSh",
            "ConnID": 2048,
            "CornerPositions": [
                [
                    -595.2125,
                    -277.0
                ],
                [
                    -595.2125,
                    -232.0
                ]
            ],
            "FirstSegmentLabelPos": [
                70.0,
                50.0
            ],
            "GroupName": "defaultGroup",
            "PortFromID": 2032,
            "PortToID": 188,
            "SegmentPositions": [
                [
                    -600.0,
                    -277.0,
                    -595.2125,
                    -277.0
                ],
                [
                    -595.2125,
                    -277.0,
                    -595.2125,
                    -232.0
                ],
                [
                    -595.2125,
                    -232.0,
                    -567.125,
                    -232.0
                ]
            ],
            "isVirtualConn": false,
            "trnsysID": 665
        },
        "Connection-2051": {
            ".__ConnectionDict__": true,
            "ConnCID": 458,
            "ConnDisplayName": "PiShTesOut",
            "ConnID": 2051,
            "CornerPositions": [
                [
                    -569.5,
                    -45.77777777777778
                ],
                [
                    -569.5,
                    -79.0
                ]
            ],
            "FirstSegmentLabelPos": [
                -10.0,
                50.0
            ],
            "GroupName": "defaultGroup",
            "PortFromID": 184,
            "PortToID": 2033,
            "SegmentPositions": [
                [
                    -515.0,
                    -45.77777777777778,
                    -569.5,
                    -45.77777777777778
                ],
                [
                    -569.5,
                    -45.77777777777778,
                    -569.5,
                    -79.0
                ],
                [
                    -569.5,
                    -79.0,
                    -600.0,
                    -79.0
                ]
            ],
            "isVirtualConn": false,
            "trnsysID": 666
        },
        "Connection-215": {
            ".__ConnectionDict__": true,
            "ConnCID": 25,
            "ConnDisplayName": "PiHpEvapIn",
            "ConnID": 215,
            "CornerPositions": [
                [
                    -974.5,
                    -288.77777777777777
                ],
                [
                    -974.5,
                    -271.3333333333333
                ]
            ],
            "FirstSegmentLabelPos": [
                70.0,
                50.0
            ],
            "GroupName": "defaultGroup",
            "PortFromID": 137,
            "PortToID": 167,
            "SegmentPositions": [
                [
                    -986.0,
                    -288.77777777777777,
                    -974.5,
                    -288.77777777777777
                ],
                [
                    -974.5,
                    -288.77777777777777,
                    -974.5,
                    -271.3333333333333
                ],
                [
                    -974.5,
                    -271.3333333333333,
                    -946.0,
                    -271.3333333333333
                ]
            ],
            "isVirtualConn": false,
            "trnsysID": 63
        },
        "Connection-221": {
            ".__ConnectionDict__": true,
            "ConnCID": 27,
            "ConnDisplayName": "PiHpEvapMix",
            "ConnID": 221,
            "CornerPositions": [
                [
                    -1019.0,
                    -223.0
                ],
                [
                    -1019.0,
                    -253.0
                ]
            ],
            "FirstSegmentLabelPos": [
                70.0,
                50.0
            ],
            "GroupName": "defaultGroup",
            "PortFromID": 141,
            "PortToID": 136,
            "SegmentPositions": [
                [
                    -1024.0,
                    -223.0,
                    -1019.0,
                    -223.0
                ],
                [
                    -1019.0,
                    -223.0,
                    -1019.0,
                    -253.0
                ],
                [
                    -1019.0,
                    -253.0,
                    -1019.0,
                    -253.0
                ]
            ],
            "isVirtualConn": false,
            "trnsysID": 65
        },
        "Connection-227": {
            ".__ConnectionDict__": true,
            "ConnCID": 29,
            "ConnDisplayName": "PiIceToHp",
            "ConnID": 227,
            "CornerPositions": [
                [
                    -1085.5,
                    -288.0
                ],
                [
                    -1085.5,
                    -288.77777777777777
                ]
            ],
            "FirstSegmentLabelPos": [
                70.0,
                50.0
            ],
            "GroupName": "defaultGroup",
            "PortFromID": 133,
            "PortToID": 135,
            "SegmentPositions": [
                [
                    -1153.0,
                    -293.0,
                    -1085.5,
                    -288.0
                ],
                [
                    -1085.5,
                    -288.0,
                    -1085.5,
                    -288.77777777777777
                ],
                [
                    -1085.5,
                    -288.77777777777777,
                    -1052.0,
                    -288.77777777777777
                ]
            ],
            "isVirtualConn": false,
            "trnsysID": 67
        },
        "Connection-2298": {
            ".__ConnectionDict__": true,
            "ConnCID": 515,
            "ConnDisplayName": "PiDivDhwShCol",
            "ConnID": 2298,
            "CornerPositions": [
                [
                    -912.5,
                    -542.7777777777778
                ],
                [
                    -912.5,
                    -489.77777777777777
                ]
            ],
            "FirstSegmentLabelPos": [
                70.0,
                50.0
            ],
            "GroupName": "defaultGroup",
            "PortFromID": 200,
            "PortToID": 2297,
            "SegmentPositions": [
                [
                    -948.0,
                    -542.7777777777778,
                    -912.5,
                    -542.7777777777778
                ],
                [
                    -912.5,
                    -542.7777777777778,
                    -912.5,
                    -489.77777777777777
                ],
                [
                    -912.5,
                    -489.77777777777777,
                    -877.0,
                    -489.77777777777777
                ]
            ],
            "isVirtualConn": false,
            "trnsysID": 743
        },
        "Connection-230": {
            ".__ConnectionDict__": true,
            "ConnCID": 30,
            "ConnDisplayName": "PiTeeOutIceIn",
            "ConnID": 230,
            "CornerPositions": [
                [
                    -1176.0,
                    -129.0
                ],
                [
                    -1176.0,
                    -6.0
                ]
            ],
            "FirstSegmentLabelPos": [
                70.0,
                50.0
            ],
            "GroupName": "defaultGroup",
            "PortFromID": 128,
            "PortToID": 214,
            "SegmentPositions": [
                [
                    -1180.125,
                    -139.0,
                    -1176.0,
                    -129.0
                ],
                [
                    -1176.0,
                    -129.0,
                    -1176.0,
                    -6.0
                ],
                [
                    -1176.0,
                    -6.0,
                    -1129.0,
                    -6.0
                ]
            ],
            "isVirtualConn": false,
            "trnsysID": 68
        },
        "Connection-2301": {
            ".__ConnectionDict__": true,
            "ConnCID": 516,
            "ConnDisplayName": "PiOutHxTes",
            "ConnID": 2301,
            "CornerPositions": [
                [
                    -767.5,
                    -489.77777777777777
                ],
                [
                    -767.5,
                    -479.0
                ]
            ],
            "FirstSegmentLabelPos": [
                70.0,
                50.0
            ],
            "GroupName": "defaultGroup",
            "PortFromID": 2295,
            "PortToID": 1978,
            "SegmentPositions": [
                [
                    -811.0,
                    -489.77777777777777,
                    -767.5,
                    -489.77777777777777
                ],
                [
                    -767.5,
                    -489.77777777777777,
                    -767.5,
                    -479.0
                ],
                [
                    -767.5,
                    -479.0,
                    -724.0,
                    -479.0
                ]
            ],
            "isVirtualConn": false,
            "trnsysID": 744
        },
        "Connection-2307": {
            ".__ConnectionDict__": true,
            "ConnCID": 518,
            "ConnDisplayName": "PiColOut",
            "ConnID": 2307,
            "CornerPositions": [
                [
                    -1181.5,
                    -647.225
                ],
                [
                    -1181.5,
                    -647.0
                ]
            ],
            "FirstSegmentLabelPos": [
                -10.0,
                50.0
            ],
            "GroupName": "defaultGroup",
            "PortFromID": 196,
            "PortToID": 49,
            "SegmentPositions": [
                [
                    -1158.0,
                    -647.125,
                    -1181.5,
                    -647.225
                ],
                [
                    -1181.5,
                    -647.225,
                    -1181.5,
                    -647.0
                ],
                [
                    -1181.5,
                    -647.0,
                    -1211.0,
                    -647.0
                ]
            ],
            "isVirtualConn": false,
            "trnsysID": 746
        },
        "Connection-2310": {
            ".__ConnectionDict__": true,
            "ConnCID": 519,
            "ConnDisplayName": "PiHpOutDiv",
            "ConnID": 2310,
            "CornerPositions": [
                [
                    -1105.0,
                    -162.0
                ],
                [
                    -1105.0,
                    -181.575
                ]
            ],
            "FirstSegmentLabelPos": [
                70.0,
                50.0
            ],
            "GroupName": "defaultGroup",
            "PortFromID": 129,
            "PortToID": 139,
            "SegmentPositions": [
                [
                    -1138.0,
                    -167.0,
                    -1105.0,
                    -162.0
                ],
                [
                    -1105.0,
                    -162.0,
                    -1105.0,
                    -181.575
                ],
                [
                    -1105.0,
                    -181.575,
                    -1052.0,
                    -180.875
                ]
            ],
            "isVirtualConn": false,
            "trnsysID": 747
        },
        "Connection-2313": {
            ".__ConnectionDict__": true,
            "ConnCID": 520,
            "ConnDisplayName": "PiHpCondOut",
            "ConnID": 2313,
            "CornerPositions": [
                [
                    -828.0,
                    -271.3333333333333
                ],
                [
                    -828.0,
                    -379.0
                ]
            ],
            "FirstSegmentLabelPos": [
                70.0,
                50.0
            ],
            "GroupName": "defaultGroup",
            "PortFromID": 168,
            "PortToID": 174,
            "SegmentPositions": [
                [
                    -830.0,
                    -271.3333333333333,
                    -828.0,
                    -271.3333333333333
                ],
                [
                    -828.0,
                    -271.3333333333333,
                    -828.0,
                    -379.0
                ],
                [
                    -828.0,
                    -379.0,
                    -885.7777777777778,
                    -379.0
                ]
            ],
            "isVirtualConn": false,
            "trnsysID": 748
        },
        "Connection-2316": {
            ".__ConnectionDict__": true,
            "ConnCID": 521,
            "ConnDisplayName": "PiOutHxTesSh",
            "ConnID": 2316,
            "CornerPositions": [
                [
                    -745.0,
                    -454.0
                ],
                [
                    -745.0,
                    -94.0
                ]
            ],
            "FirstSegmentLabelPos": [
                70.0,
                50.0
            ],
            "GroupName": "defaultGroup",
            "PortFromID": 2296,
            "PortToID": 2281,
            "SegmentPositions": [
                [
                    -844.0,
                    -454.0,
                    -745.0,
                    -454.0
                ],
                [
                    -745.0,
                    -454.0,
                    -745.0,
                    -94.0
                ],
                [
                    -745.0,
                    -94.0,
                    -716.0,
                    -94.0
                ]
            ],
            "isVirtualConn": false,
            "trnsysID": 749
        },
        "Connection-2323": {
            ".__ConnectionDict__": true,
            "ConnCID": 522,
            "ConnDisplayName": "PiColDivDhwSh",
            "ConnID": 2323,
            "CornerPositions": [
                [
                    -1038.0,
                    -647.225
                ],
                [
                    -1038.0,
                    -648.225
                ]
            ],
            "FirstSegmentLabelPos": [
                70.0,
                50.0
            ],
            "GroupName": "defaultGroup",
            "PortFromID": 197,
            "PortToID": 2320,
            "SegmentPositions": [
                [
                    -1102.0,
                    -647.125,
                    -1038.0,
                    -647.225
                ],
                [
                    -1038.0,
                    -647.225,
                    -1038.0,
                    -648.225
                ],
                [
                    -1038.0,
                    -648.225,
                    -984.0,
                    -648.125
                ]
            ],
            "isVirtualConn": false,
            "trnsysID": 751
        },
        "Connection-2326": {
            ".__ConnectionDict__": true,
            "ConnCID": 523,
            "ConnDisplayName": "PiInHxTes",
            "ConnID": 2326,
            "CornerPositions": [
                [
                    -746.0,
                    -648.225
                ],
                [
                    -746.0,
                    -521.0
                ],
                [
                    -746.0,
                    -521.0
                ],
                [
                    -746.0,
                    -519.0
                ]
            ],
            "FirstSegmentLabelPos": [
                70.0,
                50.0
            ],
            "GroupName": "defaultGroup",
            "PortFromID": 2321,
            "PortToID": 1977,
            "SegmentPositions": [
                [
                    -928.0,
                    -648.125,
                    -746.0,
                    -648.225
                ],
                [
                    -746.0,
                    -648.225,
                    -746.0,
                    -521.0
                ],
                [
                    -746.0,
                    -521.0,
                    -746.0,
                    -521.0
                ],
                [
                    -746.0,
                    -521.0,
                    -746.0,
                    -519.0
                ],
                [
                    -746.0,
                    -519.0,
                    -724.0,
                    -519.0
                ]
            ],
            "isVirtualConn": false,
            "trnsysID": 752
        },
        "Connection-2329": {
            ".__ConnectionDict__": true,
            "ConnCID": 524,
            "ConnDisplayName": "PiInHxTesSh",
            "ConnID": 2329,
            "CornerPositions": [
                [
                    -770.0,
                    -606.8
                ],
                [
                    -770.0,
                    -134.0
                ]
            ],
            "FirstSegmentLabelPos": [
                70.0,
                50.0
            ],
            "GroupName": "defaultGroup",
            "PortFromID": 2322,
            "PortToID": 2280,
            "SegmentPositions": [
                [
                    -956.0,
                    -606.0,
                    -770.0,
                    -606.8
                ],
                [
                    -770.0,
                    -606.8,
                    -770.0,
                    -134.0
                ],
                [
                    -770.0,
                    -134.0,
                    -716.0,
                    -134.0
                ]
            ],
            "isVirtualConn": false,
            "trnsysID": 753
        },
        "Connection-233": {
            ".__ConnectionDict__": true,
            "ConnCID": 31,
            "ConnDisplayName": "PiTeeColToHpIn",
            "ConnID": 233,
            "CornerPositions": [
                [
                    -1086.2125,
                    -255.0
                ],
                [
                    -1086.2125,
                    92.0
                ]
            ],
            "FirstSegmentLabelPos": [
                70.0,
                50.0
            ],
            "GroupName": "defaultGroup",
            "PortFromID": 132,
            "PortToID": 210,
            "SegmentPositions": [
                [
                    -1195.125,
                    -265.0,
                    -1086.2125,
                    -255.0
                ],
                [
                    -1086.2125,
                    -255.0,
                    -1086.2125,
                    92.0
                ],
                [
                    -1086.2125,
                    92.0,
                    -1038.0,
                    92.0
                ]
            ],
            "isVirtualConn": false,
            "trnsysID": 69
        },
        "Connection-242": {
            ".__ConnectionDict__": true,
            "ConnCID": 34,
            "ConnDisplayName": "PiPuCoolIn",
            "ConnID": 242,
            "CornerPositions": [
                [
                    -949.5,
                    35.425000000000004
                ],
                [
                    -949.5,
                    71.0
                ]
            ],
            "FirstSegmentLabelPos": [
                70.0,
                50.0
            ],
            "GroupName": "defaultGroup",
            "PortFromID": 213,
            "PortToID": 181,
            "SegmentPositions": [
                [
                    -1101.0,
                    36.125,
                    -949.5,
                    35.425000000000004
                ],
                [
                    -949.5,
                    35.425000000000004,
                    -949.5,
                    71.0
                ],
                [
                    -949.5,
                    71.0,
                    -808.0,
                    72.5
                ]
            ],
            "isVirtualConn": false,
            "trnsysID": 72
        },
        "Connection-245": {
            ".__ConnectionDict__": true,
            "ConnCID": 35,
            "ConnDisplayName": "PiHxCoolBriIn",
            "ConnID": 245,
            "CornerPositions": [
                [
                    -703.0,
                    71.0
                ],
                [
                    -703.0,
                    71.0
                ]
            ],
            "FirstSegmentLabelPos": [
                70.0,
                50.0
            ],
            "GroupName": "defaultGroup",
            "PortFromID": 182,
            "PortToID": 176,
            "SegmentPositions": [
                [
                    -760.0,
                    72.5,
                    -703.0,
                    71.0
                ],
                [
                    -703.0,
                    71.0,
                    -703.0,
                    71.0
                ],
                [
                    -703.0,
                    71.0,
                    -646.0,
                    71.0
                ]
            ],
            "isVirtualConn": false,
            "trnsysID": 73
        },
        "Connection-248": {
            ".__ConnectionDict__": true,
            "ConnCID": 36,
            "ConnDisplayName": "PiHxCoolBriOut",
            "ConnID": 248,
            "CornerPositions": [
                [
                    -823.0,
                    134.0
                ],
                [
                    -823.0,
                    133.425
                ]
            ],
            "FirstSegmentLabelPos": [
                -10.0,
                50.0
            ],
            "GroupName": "defaultGroup",
            "PortFromID": 178,
            "PortToID": 209,
            "SegmentPositions": [
                [
                    -646.0,
                    134.0,
                    -823.0,
                    134.0
                ],
                [
                    -823.0,
                    134.0,
                    -823.0,
                    133.425
                ],
                [
                    -823.0,
                    133.425,
                    -1010.0,
                    134.125
                ]
            ],
            "isVirtualConn": false,
            "trnsysID": 74
        },
        "Connection-254": {
            ".__ConnectionDict__": true,
            "ConnCID": 38,
            "ConnDisplayName": "PiColToIce",
            "ConnID": 254,
            "CornerPositions": [
                [
                    -1195.0,
                    -321.0
                ],
                [
                    -1195.0,
                    -605.8
                ]
            ],
            "FirstSegmentLabelPos": [
                71.0,
                100.0
            ],
            "GroupName": "defaultGroup",
            "PortFromID": 131,
            "PortToID": 198,
            "SegmentPositions": [
                [
                    -1195.125,
                    -321.0,
                    -1195.0,
                    -321.0
                ],
                [
                    -1195.0,
                    -321.0,
                    -1195.0,
                    -605.8
                ],
                [
                    -1195.0,
                    -605.8,
                    -1130.0,
                    -605.0
                ]
            ],
            "isVirtualConn": false,
            "trnsysID": 76
        },
        "Connection-260": {
            ".__ConnectionDict__": true,
            "ConnCID": 40,
            "ConnDisplayName": "PiColIn",
            "ConnID": 260,
            "CornerPositions": [
                [
                    -1119.5,
                    -542.0
                ],
                [
                    -1119.5,
                    -567.0
                ]
            ],
            "FirstSegmentLabelPos": [
                -10.0,
                50.0
            ],
            "GroupName": "defaultGroup",
            "PortFromID": 205,
            "PortToID": 50,
            "SegmentPositions": [
                [
                    -1100.0,
                    -540.5,
                    -1119.5,
                    -542.0
                ],
                [
                    -1119.5,
                    -542.0,
                    -1119.5,
                    -567.0
                ],
                [
                    -1119.5,
                    -567.0,
                    -1211.0,
                    -567.0
                ]
            ],
            "isVirtualConn": false,
            "trnsysID": 78
        },
        "Connection-290": {
            ".__ConnectionDict__": true,
            "ConnCID": 50,
            "ConnDisplayName": "PiHxCoolWatIn",
            "ConnID": 290,
            "CornerPositions": [
                [
                    -509.0,
                    -10.0
                ],
                [
                    -509.0,
                    71.0
                ]
            ],
            "FirstSegmentLabelPos": [
                50.0,
                50.0
            ],
            "GroupName": "CircnLoop",
            "PortFromID": 185,
            "PortToID": 177,
            "SegmentPositions": [
                [
                    -482.0,
                    -10.0,
                    -509.0,
                    -10.0
                ],
                [
                    -509.0,
                    -10.0,
                    -509.0,
                    71.0
                ],
                [
                    -509.0,
                    71.0,
                    -530.0,
                    71.0
                ]
            ],
            "isVirtualConn": false,
            "trnsysID": 88
        },
        "Connection-299": {
            ".__ConnectionDict__": true,
            "ConnCID": 53,
            "ConnDisplayName": "PiTeeMixSHIn",
            "ConnID": 299,
            "CornerPositions": [
                [
                    -423.0,
                    -185.225
                ],
                [
                    -423.0,
                    -199.0
                ]
            ],
            "FirstSegmentLabelPos": [
                -10.0,
                50.0
            ],
            "GroupName": "CircnLoop",
            "PortFromID": 68,
            "PortToID": 190,
            "SegmentPositions": [
                [
                    -400.0,
                    -185.125,
                    -423.0,
                    -185.225
                ],
                [
                    -423.0,
                    -185.225,
                    -423.0,
                    -199.0
                ],
                [
                    -423.0,
                    -199.0,
                    -525.0,
                    -204.0
                ]
            ],
            "isVirtualConn": false,
            "trnsysID": 91
        },
        "Connection-302": {
            ".__ConnectionDict__": true,
            "ConnCID": 54,
            "ConnDisplayName": "PiHxCoolWatOut",
            "ConnID": 302,
            "CornerPositions": [
                [
                    -457.425,
                    -166.0
                ],
                [
                    -457.425,
                    134.0
                ]
            ],
            "FirstSegmentLabelPos": [
                70.0,
                50.0
            ],
            "GroupName": "CircnLoop",
            "PortFromID": 189,
            "PortToID": 179,
            "SegmentPositions": [
                [
                    -567.125,
                    -176.0,
                    -457.425,
                    -166.0
                ],
                [
                    -457.425,
                    -166.0,
                    -457.425,
                    134.0
                ],
                [
                    -457.425,
                    134.0,
                    -530.0,
                    134.0
                ]
            ],
            "isVirtualConn": false,
            "trnsysID": 92
        },
        "Connection-305": {
            ".__ConnectionDict__": true,
            "ConnCID": 55,
            "ConnDisplayName": "PiDivSHCool",
            "ConnID": 305,
            "CornerPositions": [
                [
                    -423.0,
                    -45.77777777777778
                ],
                [
                    -423.0,
                    -92.22222222222223
                ]
            ],
            "FirstSegmentLabelPos": [
                70.0,
                50.0
            ],
            "GroupName": "CircnLoop",
            "PortFromID": 186,
            "PortToID": 61,
            "SegmentPositions": [
                [
                    -449.0,
                    -45.77777777777778,
                    -423.0,
                    -45.77777777777778
                ],
                [
                    -423.0,
                    -45.77777777777778,
                    -423.0,
                    -92.22222222222223
                ],
                [
                    -423.0,
                    -92.22222222222223,
                    -265.0,
                    -92.22222222222223
                ]
            ],
            "isVirtualConn": false,
            "trnsysID": 93
        },
        "Connection-3069": {
            ".__ConnectionDict__": true,
            "ConnCID": 686,
            "ConnDisplayName": "PiPuDhwOut",
            "ConnID": 3069,
            "CornerPositions": [
                [
                    -325.0,
                    -447.0
                ],
                [
                    -325.0,
                    -448.0
                ],
                [
                    -372.0,
                    -448.0
                ],
                [
                    -372.0,
                    -447.22222222222223
                ]
            ],
            "FirstSegmentLabelPos": [
                -10.0,
                50.0
            ],
            "GroupName": "defaultGroup",
            "PortFromID": 324,
            "PortToID": 3068,
            "SegmentPositions": [
                [
                    -324.0,
                    -445.5,
                    -325.0,
                    -447.0
                ],
                [
                    -325.0,
                    -447.0,
                    -325.0,
                    -448.0
                ],
                [
                    -325.0,
                    -448.0,
                    -372.0,
                    -448.0
                ],
                [
                    -372.0,
                    -448.0,
                    -372.0,
                    -447.22222222222223
                ],
                [
                    -372.0,
                    -447.22222222222223,
                    -410.0,
                    -447.22222222222223
                ]
            ],
            "isVirtualConn": false,
            "trnsysID": 991
        },
        "Connection-3072": {
            ".__ConnectionDict__": true,
            "ConnCID": 687,
            "ConnDisplayName": "PiCircIn",
            "ConnID": 3072,
            "CornerPositions": [
                [
                    -525.5,
                    -483.0
                ],
                [
                    -525.5,
                    -607.0
                ]
            ],
            "FirstSegmentLabelPos": [
                70.0,
                50.0
            ],
            "GroupName": "defaultGroup",
            "PortFromID": 3067,
            "PortToID": 1993,
            "SegmentPositions": [
                [
                    -443.0,
                    -483.0,
                    -525.5,
                    -483.0
                ],
                [
                    -525.5,
                    -483.0,
                    -525.5,
                    -607.0
                ],
                [
                    -525.5,
                    -607.0,
                    -608.0,
                    -607.0
                ]
            ],
            "isVirtualConn": false,
            "trnsysID": 992
        },
        "Connection-3078": {
            ".__ConnectionDict__": true,
            "ConnCID": 689,
            "ConnDisplayName": "PiTesDhwIn",
            "ConnID": 3078,
            "CornerPositions": [
                [
                    -542.0,
                    -447.22222222222223
                ],
                [
                    -542.0,
                    -464.0
                ]
            ],
            "FirstSegmentLabelPos": [
                -10.0,
                50.0
            ],
            "GroupName": "defaultGroup",
            "PortFromID": 3066,
            "PortToID": 1988,
            "SegmentPositions": [
                [
                    -476.0,
                    -447.22222222222223,
                    -542.0,
                    -447.22222222222223
                ],
                [
                    -542.0,
                    -447.22222222222223,
                    -542.0,
                    -464.0
                ],
                [
                    -542.0,
                    -464.0,
                    -608.0,
                    -464.0
                ]
            ],
            "isVirtualConn": false,
            "trnsysID": 994
        },
        "Connection-3085": {
            ".__ConnectionDict__": true,
            "ConnCID": 690,
            "ConnDisplayName": "PiPuCircOut",
            "ConnID": 3085,
            "CornerPositions": [
                [
                    -61.0,
                    -509.0
                ],
                [
                    -61.0,
                    -465.0
                ]
            ],
            "FirstSegmentLabelPos": [
                -10.0,
                50.0
            ],
            "GroupName": "defaultGroup",
            "PortFromID": 333,
            "PortToID": 3084,
            "SegmentPositions": [
                [
                    -52.0,
                    -507.5,
                    -61.0,
                    -509.0
                ],
                [
                    -61.0,
                    -509.0,
                    -61.0,
                    -465.0
                ],
                [
                    -61.0,
                    -465.0,
                    -75.0,
                    -465.0
                ]
            ],
            "isVirtualConn": false,
            "trnsysID": 996
        },
        "Connection-3092": {
            ".__ConnectionDict__": true,
            "ConnCID": 691,
            "ConnDisplayName": "PiPuCircIn",
            "ConnID": 3092,
            "CornerPositions": [
                [
                    -2.5,
                    -509.0
                ],
                [
                    -2.5,
                    -644.8
                ]
            ],
            "FirstSegmentLabelPos": [
                70.0,
                50.0
            ],
            "GroupName": "defaultGroup",
            "PortFromID": 332,
            "PortToID": 3091,
            "SegmentPositions": [
                [
                    -4.0,
                    -507.5,
                    -2.5,
                    -509.0
                ],
                [
                    -2.5,
                    -509.0,
                    -2.5,
                    -644.8
                ],
                [
                    -2.5,
                    -644.8,
                    -6.0,
                    -644.0
                ]
            ],
            "isVirtualConn": false,
            "trnsysID": 998
        },
        "Connection-3095": {
            ".__ConnectionDict__": true,
            "ConnCID": 692,
            "ConnDisplayName": "PiDhwDemand",
            "ConnID": 3095,
            "CornerPositions": [
                [
                    55.0,
                    -686.225
                ],
                [
                    55.0,
                    -735.095
                ]
            ],
            "FirstSegmentLabelPos": [
                70.0,
                50.0
            ],
            "GroupName": "defaultGroup",
            "PortFromID": 3090,
            "PortToID": 78,
            "SegmentPositions": [
                [
                    22.0,
                    -686.125,
                    55.0,
                    -686.225
                ],
                [
                    55.0,
                    -686.225,
                    55.0,
                    -735.095
                ],
                [
                    55.0,
                    -735.095,
                    78.0,
                    -735.5
                ]
            ],
            "isVirtualConn": false,
            "trnsysID": 999
        },
        "Connection-3098": {
            ".__ConnectionDict__": true,
            "ConnCID": 693,
            "ConnDisplayName": "PiDhwSecOut",
            "ConnID": 3098,
            "CornerPositions": [
                [
                    -75.5,
                    -686.225
                ],
                [
                    -75.5,
                    -637.0
                ]
            ],
            "FirstSegmentLabelPos": [
                -10.0,
                50.0
            ],
            "GroupName": "defaultGroup",
            "PortFromID": 3089,
            "PortToID": 310,
            "SegmentPositions": [
                [
                    -34.0,
                    -686.125,
                    -75.5,
                    -686.225
                ],
                [
                    -75.5,
                    -686.225,
                    -75.5,
                    -637.0
                ],
                [
                    -75.5,
                    -637.0,
                    -123.0,
                    -637.0
                ]
            ],
            "isVirtualConn": false,
            "trnsysID": 1000
        },
        "Connection-3101": {
            ".__ConnectionDict__": true,
            "ConnCID": 694,
            "ConnDisplayName": "PiHxDhwSecIn",
            "ConnID": 3101,
            "CornerPositions": [
                [
                    -110.0,
                    -574.0
                ],
                [
                    -110.0,
                    -423.575
                ]
            ],
            "FirstSegmentLabelPos": [
                70.0,
                50.0
            ],
            "GroupName": "defaultGroup",
            "PortFromID": 312,
            "PortToID": 3082,
            "SegmentPositions": [
                [
                    -123.0,
                    -574.0,
                    -110.0,
                    -574.0
                ],
                [
                    -110.0,
                    -574.0,
                    -110.0,
                    -423.575
                ],
                [
                    -110.0,
                    -423.575,
                    -103.0,
                    -422.875
                ]
            ],
            "isVirtualConn": false,
            "trnsysID": 1001
        },
        "Connection-3104": {
            ".__ConnectionDict__": true,
            "ConnCID": 695,
            "ConnDisplayName": "PiDhwMains",
            "ConnID": 3104,
            "CornerPositions": [
                [
                    14.5,
                    -423.575
                ],
                [
                    14.5,
                    -466.0
                ]
            ],
            "FirstSegmentLabelPos": [
                70.0,
                50.0
            ],
            "GroupName": "defaultGroup",
            "PortFromID": 3083,
            "PortToID": 80,
            "SegmentPositions": [
                [
                    -47.0,
                    -422.875,
                    14.5,
                    -423.575
                ],
                [
                    14.5,
                    -423.575,
                    14.5,
                    -466.0
                ],
                [
                    14.5,
                    -466.0,
                    66.0,
                    -466.0
                ]
            ],
            "isVirtualConn": false,
            "trnsysID": 1002
        },
        "Connection-3111": {
            ".__ConnectionDict__": true,
            "ConnCID": 696,
            "ConnDisplayName": "PiHpToTesSHOut",
            "ConnID": 3111,
            "CornerPositions": [
                [
                    -738.0,
                    -77.57499999999999
                ],
                [
                    -738.0,
                    -79.0
                ]
            ],
            "FirstSegmentLabelPos": [
                70.0,
                50.0
            ],
            "GroupName": "defaultGroup",
            "PortFromID": 3109,
            "PortToID": 2028,
            "SegmentPositions": [
                [
                    -767.0,
                    -76.875,
                    -738.0,
                    -77.57499999999999
                ],
                [
                    -738.0,
                    -77.57499999999999,
                    -738.0,
                    -79.0
                ],
                [
                    -738.0,
                    -79.0,
                    -716.0,
                    -79.0
                ]
            ],
            "isVirtualConn": false,
            "trnsysID": 1004
        },
        "Connection-3114": {
            ".__ConnectionDict__": true,
            "ConnCID": 697,
            "ConnDisplayName": "PiHpToTesDHWOut",
            "ConnID": 3114,
            "CornerPositions": [
                [
                    -758.5,
                    -119.0
                ],
                [
                    -758.5,
                    -464.0
                ]
            ],
            "FirstSegmentLabelPos": [
                70.0,
                50.0
            ],
            "GroupName": "defaultGroup",
            "PortFromID": 3110,
            "PortToID": 1983,
            "SegmentPositions": [
                [
                    -795.0,
                    -119.0,
                    -758.5,
                    -119.0
                ],
                [
                    -758.5,
                    -119.0,
                    -758.5,
                    -464.0
                ],
                [
                    -758.5,
                    -464.0,
                    -724.0,
                    -464.0
                ]
            ],
            "isVirtualConn": false,
            "trnsysID": 1005
        },
        "Connection-3117": {
            ".__ConnectionDict__": true,
            "ConnCID": 698,
            "ConnDisplayName": "PiHpInPu",
            "ConnID": 3117,
            "CornerPositions": [
                [
                    -826.0,
                    -77.57499999999999
                ],
                [
                    -826.0,
                    -161.0
                ]
            ],
            "FirstSegmentLabelPos": [
                -10.0,
                50.0
            ],
            "GroupName": "defaultGroup",
            "PortFromID": 3108,
            "PortToID": 1618,
            "SegmentPositions": [
                [
                    -823.0,
                    -76.875,
                    -826.0,
                    -77.57499999999999
                ],
                [
                    -826.0,
                    -77.57499999999999,
                    -826.0,
                    -161.0
                ],
                [
                    -826.0,
                    -161.0,
                    -824.5,
                    -161.0
                ]
            ],
            "isVirtualConn": false,
            "trnsysID": 1006
        },
        "Connection-325": {
            ".__ConnectionDict__": true,
            "ConnCID": 59,
            "ConnDisplayName": "PiHxDhwOut",
            "ConnID": 325,
            "CornerPositions": [
                [
                    -242.0,
                    -574.0
                ],
                [
                    -242.0,
                    -447.0
                ],
                [
                    -243.0,
                    -447.0
                ],
                [
                    -243.0,
                    -447.0
                ]
            ],
            "FirstSegmentLabelPos": [
                -10.0,
                50.0
            ],
            "GroupName": "defaultGroup",
            "PortFromID": 311,
            "PortToID": 323,
            "SegmentPositions": [
                [
                    -239.0,
                    -574.0,
                    -242.0,
                    -574.0
                ],
                [
                    -242.0,
                    -574.0,
                    -242.0,
                    -447.0
                ],
                [
                    -242.0,
                    -447.0,
                    -243.0,
                    -447.0
                ],
                [
                    -243.0,
                    -447.0,
                    -243.0,
                    -447.0
                ],
                [
                    -243.0,
                    -447.0,
                    -276.0,
                    -445.5
                ]
            ],
            "isVirtualConn": false,
            "trnsysID": 100
        },
        "Connection-3265": {
            ".__ConnectionDict__": true,
            "ConnCID": 730,
            "ConnDisplayName": "PiTesDhwOut",
            "ConnID": 3265,
            "CornerPositions": [
                [
                    -555.5,
                    -662.0
                ],
                [
                    -555.5,
                    -662.7777777777778
                ]
            ],
            "FirstSegmentLabelPos": [
                70.0,
                50.0
            ],
            "GroupName": "defaultGroup",
            "PortFromID": 1987,
            "PortToID": 3262,
            "SegmentPositions": [
                [
                    -608.0,
                    -662.0,
                    -555.5,
                    -662.0
                ],
                [
                    -555.5,
                    -662.0,
                    -555.5,
                    -662.7777777777778
                ],
                [
                    -555.5,
                    -662.7777777777778,
                    -503.0,
                    -662.7777777777778
                ]
            ],
            "isVirtualConn": false,
            "trnsysID": 1054
        },
        "Connection-3268": {
            ".__ConnectionDict__": true,
            "ConnCID": 731,
            "ConnDisplayName": "PiHxDhwIn",
            "ConnID": 3268,
            "CornerPositions": [
                [
                    -338.0,
                    -662.7777777777778
                ],
                [
                    -338.0,
                    -637.0
                ]
            ],
            "FirstSegmentLabelPos": [
                70.0,
                50.0
            ],
            "GroupName": "defaultGroup",
            "PortFromID": 3264,
            "PortToID": 309,
            "SegmentPositions": [
                [
                    -437.0,
                    -662.7777777777778,
                    -338.0,
                    -662.7777777777778
                ],
                [
                    -338.0,
                    -662.7777777777778,
                    -338.0,
                    -637.0
                ],
                [
                    -338.0,
                    -637.0,
                    -239.0,
                    -637.0
                ]
            ],
            "isVirtualConn": false,
            "trnsysID": 1055
        },
        "Connection-3271": {
            ".__ConnectionDict__": true,
            "ConnCID": 732,
            "ConnDisplayName": "PiCircOut",
            "ConnID": 3271,
            "CornerPositions": [
                [
                    -539.0,
                    -651.0
                ],
                [
                    -539.0,
                    -627.0
                ]
            ],
            "FirstSegmentLabelPos": [
                70.0,
                50.0
            ],
            "GroupName": "defaultGroup",
            "PortFromID": 1992,
            "PortToID": 3263,
            "SegmentPositions": [
                [
                    -608.0,
                    -651.0,
                    -539.0,
                    -651.0
                ],
                [
                    -539.0,
                    -651.0,
                    -539.0,
                    -627.0
                ],
                [
                    -539.0,
                    -627.0,
                    -470.0,
                    -627.0
                ]
            ],
            "isVirtualConn": false,
            "trnsysID": 1056
        },
        "Connection-3414": {
            ".__ConnectionDict__": true,
            "ConnCID": 765,
            "ConnDisplayName": "PiIceOut",
            "ConnID": 3414,
            "CornerPositions": [
                [
                    -1145.5,
                    114.6923076923077
                ],
                [
                    -1145.5,
                    133.425
                ]
            ],
            "FirstSegmentLabelPos": [
                50.0,
                50.0
            ],
            "GroupName": "defaultGroup",
            "PortFromID": 125,
            "PortToID": 208,
            "SegmentPositions": [
                [
                    -1225.0,
                    119.3076923076923,
                    -1145.5,
                    114.6923076923077
                ],
                [
                    -1145.5,
                    114.6923076923077,
                    -1145.5,
                    133.425
                ],
                [
                    -1145.5,
                    133.425,
                    -1066.0,
                    134.125
                ]
            ],
            "isVirtualConn": false,
            "trnsysID": 1103
        },
        "Connection-3417": {
            ".__ConnectionDict__": true,
            "ConnCID": 766,
            "ConnDisplayName": "PiIceIn",
            "ConnID": 3417,
            "CornerPositions": [
                [
                    -1191.0,
                    35.425000000000004
                ],
                [
                    -1191.0,
                    34.30769230769231
                ]
            ],
            "FirstSegmentLabelPos": [
                -10.0,
                50.0
            ],
            "GroupName": "defaultGroup",
            "PortFromID": 212,
            "PortToID": 124,
            "SegmentPositions": [
                [
                    -1157.0,
                    36.125,
                    -1191.0,
                    35.425000000000004
                ],
                [
                    -1191.0,
                    35.425000000000004,
                    -1191.0,
                    34.30769230769231
                ],
                [
                    -1191.0,
                    34.30769230769231,
                    -1225.0,
                    34.69230769230769
                ]
            ],
            "isVirtualConn": false,
            "trnsysID": 1104
        },
        "Connection-355": {
            ".__ConnectionDict__": true,
            "ConnCID": 68,
            "ConnDisplayName": "PiColPuIn",
            "ConnID": 355,
            "CornerPositions": [
                [
                    -1033.0,
                    -542.7777777777778
                ],
                [
                    -1033.0,
                    -542.0
                ]
            ],
            "FirstSegmentLabelPos": [
                -10.0,
                50.0
            ],
            "GroupName": "defaultGroup",
            "PortFromID": 202,
            "PortToID": 204,
            "SegmentPositions": [
                [
                    -1014.0,
                    -542.7777777777778,
                    -1033.0,
                    -542.7777777777778
                ],
                [
                    -1033.0,
                    -542.7777777777778,
                    -1033.0,
                    -542.0
                ],
                [
                    -1033.0,
                    -542.0,
                    -1052.0,
                    -540.5
                ]
            ],
            "isVirtualConn": false,
            "trnsysID": 110
        },
        "Connection-361": {
            ".__ConnectionDict__": true,
            "ConnCID": 70,
            "ConnDisplayName": "PiIceToCol",
            "ConnID": 361,
            "CornerPositions": [
                [
                    -1179.2125,
                    -507.0
                ],
                [
                    -1179.2125,
                    -195.0
                ]
            ],
            "FirstSegmentLabelPos": [
                70.0,
                50.0
            ],
            "GroupName": "defaultGroup",
            "PortFromID": 201,
            "PortToID": 127,
            "SegmentPositions": [
                [
                    -981.0,
                    -507.0,
                    -1179.2125,
                    -507.0
                ],
                [
                    -1179.2125,
                    -507.0,
                    -1179.2125,
                    -195.0
                ],
                [
                    -1179.2125,
                    -195.0,
                    -1180.125,
                    -195.0
                ]
            ],
            "isVirtualConn": false,
            "trnsysID": 112
        },
        "Connection-367": {
            ".__ConnectionDict__": true,
            "ConnCID": 71,
            "ConnDisplayName": "PiHpOutPu",
            "ConnID": 367,
            "CornerPositions": [
                [
                    -985.5,
                    -183.0
                ],
                [
                    -985.5,
                    -181.575
                ]
            ],
            "FirstSegmentLabelPos": [
                -10.0,
                50.0
            ],
            "GroupName": "defaultGroup",
            "PortFromID": 366,
            "PortToID": 140,
            "SegmentPositions": [
                [
                    -977.0,
                    -181.5,
                    -985.5,
                    -183.0
                ],
                [
                    -985.5,
                    -183.0,
                    -985.5,
                    -181.575
                ],
                [
                    -985.5,
                    -181.575,
                    -996.0,
                    -180.875
                ]
            ],
            "isVirtualConn": false,
            "trnsysID": 114
        },
        "Connection-370": {
            ".__ConnectionDict__": true,
            "ConnCID": 72,
            "ConnDisplayName": "PiHpEvapOut",
            "ConnID": 370,
            "CornerPositions": [
                [
                    -927.5,
                    -183.0
                ],
                [
                    -927.5,
                    -231.33333333333331
                ]
            ],
            "FirstSegmentLabelPos": [
                70.0,
                50.0
            ],
            "GroupName": "defaultGroup",
            "PortFromID": 365,
            "PortToID": 169,
            "SegmentPositions": [
                [
                    -929.0,
                    -181.5,
                    -927.5,
                    -183.0
                ],
                [
                    -927.5,
                    -183.0,
                    -927.5,
                    -231.33333333333331
                ],
                [
                    -927.5,
                    -231.33333333333331,
                    -946.0,
                    -231.33333333333331
                ]
            ],
            "isVirtualConn": false,
            "trnsysID": 115
        },
        "Connection-57": {
            ".__ConnectionDict__": true,
            "ConnCID": 9,
            "ConnDisplayName": "PiRadIn",
            "ConnID": 57,
            "CornerPositions": [
                [
                    -190.0,
                    -187.0
                ],
                [
                    -190.0,
                    -183.0
                ]
            ],
            "FirstSegmentLabelPos": [
                70.0,
                50.0
            ],
            "GroupName": "CircnLoop",
            "PortFromID": 56,
            "PortToID": 52,
            "SegmentPositions": [
                [
                    -200.0,
                    -185.5,
                    -190.0,
                    -187.0
                ],
                [
                    -190.0,
                    -187.0,
                    -190.0,
                    -183.0
                ],
                [
                    -190.0,
                    -183.0,
                    32.0,
                    -183.0
                ]
            ],
            "isVirtualConn": false,
            "trnsysID": 17
        },
        "Connection-64": {
            ".__ConnectionDict__": true,
            "ConnCID": 10,
            "ConnDisplayName": "PiRadOut",
            "ConnID": 64,
            "CornerPositions": [
                [
                    -177.5,
                    -92.22222222222223
                ],
                [
                    -177.5,
                    -93.0
                ]
            ],
            "FirstSegmentLabelPos": [
                70.0,
                50.0
            ],
            "GroupName": "CircnLoop",
            "PortFromID": 63,
            "PortToID": 53,
            "SegmentPositions": [
                [
                    -199.0,
                    -92.22222222222223,
                    -177.5,
                    -92.22222222222223
                ],
                [
                    -177.5,
                    -92.22222222222223,
                    -177.5,
                    -93.0
                ],
                [
                    -177.5,
                    -93.0,
                    32.0,
                    -93.0
                ]
            ],
            "isVirtualConn": false,
            "trnsysID": 19
        },
        "Connection-71": {
            ".__ConnectionDict__": true,
            "ConnCID": 11,
            "ConnDisplayName": "PiSHOutMix",
            "ConnID": 71,
            "CornerPositions": [
                [
                    -319.0,
                    -185.225
                ],
                [
                    -319.0,
                    -187.0
                ]
            ],
            "FirstSegmentLabelPos": [
                70.0,
                50.0
            ],
            "GroupName": "CircnLoop",
            "PortFromID": 69,
            "PortToID": 55,
            "SegmentPositions": [
                [
                    -344.0,
                    -185.125,
                    -319.0,
                    -185.225
                ],
                [
                    -319.0,
                    -185.225,
                    -319.0,
                    -187.0
                ],
                [
                    -319.0,
                    -187.0,
                    -248.0,
                    -185.5
                ]
            ],
            "isVirtualConn": false,
            "trnsysID": 21
        },
        "Connection-74": {
            ".__ConnectionDict__": true,
            "ConnCID": 12,
            "ConnDisplayName": "PiSHInMix",
            "ConnID": 74,
            "CornerPositions": [
                [
                    -368.5,
                    -128.0
                ],
                [
                    -368.5,
                    -143.8
                ]
            ],
            "FirstSegmentLabelPos": [
                70.0,
                50.0
            ],
            "GroupName": "CircnLoop",
            "PortFromID": 62,
            "PortToID": 70,
            "SegmentPositions": [
                [
                    -232.0,
                    -128.0,
                    -368.5,
                    -128.0
                ],
                [
                    -368.5,
                    -128.0,
                    -368.5,
                    -143.8
                ],
                [
                    -368.5,
                    -143.8,
                    -372.0,
                    -143.0
                ]
            ],
            "isVirtualConn": false,
            "trnsysID": 22
        },
        "IDs": {
            "GlobalId": 3761,
            "__idDct__": true,
            "globalConnID": 843,
            "trnsysID": 1216
        },
        "Strings": {
            "DiagramName": "BigIceTwoStorages",
            "__nameDct__": true
        }
    }
}