{
    "Blocks": {
        "..__GroupDct-defaultGroup": {
            ".__GroupDict__": true,
            "GroupName": "defaultGroup",
            "Position": [
                0,
                0
            ],
            "Size": [
                100,
                100
            ]
        },
        ".__BlockDct__": true,
        "Block-1": {
            ".__BlockDict__": true,
            "BlockDisplayName": "Collector",
            "BlockName": "Kollektor",
            "BlockPosition": [
                -1210.0,
                -440.0
            ],
            "FlippedH": false,
            "FlippedV": false,
            "GroupName": "defaultGroup",
            "ID": 1,
            "PortsIDIn": [
                2
            ],
            "PortsIDOut": [
                3
            ],
            "RotationN": 0,
            "trnsysID": 1
        },
        "Block-14": {
            ".__BlockDict__": true,
            "BlockDisplayName": "tapWater",
            "BlockName": "WTap",
            "BlockPosition": [
                -218.0,
                -526.0
            ],
            "FlippedH": false,
            "FlippedV": false,
            "GroupName": "defaultGroup",
            "ID": 14,
            "PortsIDIn": [
                15
            ],
            "PortsIDOut": [],
            "RotationN": 0,
            "trnsysID": 5
        },
        "Block-16": {
            ".__BlockDict__": true,
            "BlockDisplayName": "supplyWater",
            "BlockName": "WTap_main",
            "BlockPosition": [
                -210.0,
                -351.0
            ],
            "FlippedH": false,
            "FlippedV": false,
            "GroupName": "defaultGroup",
            "ID": 16,
            "PortsIDIn": [
                17
            ],
            "PortsIDOut": [],
            "RotationN": 0,
            "trnsysID": 6
        },
        "Block-18": {
            ".__BlockDict__": true,
            "BlockDisplayName": "TPieceCirc2",
            "BlockName": "TeePiece",
            "BlockPosition": [
                -398.0,
                -362.0
            ],
            "FlippedH": false,
            "FlippedV": false,
            "GroupName": "defaultGroup",
            "ID": 18,
            "PortsIDIn": [
                19,
                20
            ],
            "PortsIDOut": [
                21
            ],
            "RotationN": 0,
            "trnsysID": 7
        },
        "Block-4": {
            ".__BlockDict__": true,
            "BlockDisplayName": "PuCol",
            "BlockName": "Pump",
            "BlockPosition": [
                -999.0,
                -365.0
            ],
            "FlippedH": true,
            "FlippedV": false,
            "GroupName": "defaultGroup",
            "ID": 4,
            "PortsIDIn": [
                5
            ],
            "PortsIDOut": [
                6
            ],
            "RotationN": 0,
            "trnsysID": 2
        },
        "Block-745": {
            ".__BlockDict__": true,
            "BlockDisplayName": "Dhw",
            "BlockName": "StorageTank",
            "FlippedH": false,
            "FlippedV": false,
            "GroupName": "defaultGroup",
            "HxList": [
                {
                    "DisplayName": "HxSolar",
                    "Height": 40.0,
                    "ID": 758,
                    "Offset": [
                        0.0,
                        104.0
                    ],
                    "ParentID": 745,
                    "Port1ID": 759,
                    "Port2ID": 760,
                    "SideNr": 0,
                    "Width": 40,
                    "connTrnsysID": 320
                }
            ],
            "ID": 745,
            "PortPairList": [
                {
                    "ConnCID": 273,
                    "ConnDisName": "UntitledConn273",
                    "ConnID": 801,
                    "Port1ID": 799,
                    "Port1offset": 0.0,
                    "Port2ID": 800,
                    "Port2offset": 160.0,
                    "Side": false,
                    "trnsysID": 336
                },
                {
                    "ConnCID": 281,
                    "ConnDisName": "UntitledConn281",
                    "ConnID": 835,
                    "Port1ID": 833,
                    "Port1offset": 8.0,
                    "Port2ID": 834,
                    "Port2offset": 56.0,
                    "Side": false,
                    "trnsysID": 349
                }
            ],
            "StoragePosition": [
                -918.0,
                -489.0
            ],
            "size_h": 160.0,
            "trnsysID": 317
        },
        "Block-812": {
            ".__BlockDict__": true,
            "BlockDisplayName": "TeePieceCirc1",
            "BlockName": "TeePiece",
            "BlockPosition": [
                -399.0,
                -520.0
            ],
            "FlippedH": false,
            "FlippedV": true,
            "GroupName": "defaultGroup",
            "ID": 812,
            "PortsIDIn": [
                813,
                814
            ],
            "PortsIDOut": [
                815
            ],
            "RotationN": 0,
            "trnsysID": 341
        },
        "Block-816": {
            ".__BlockDict__": true,
            "BlockDisplayName": "PuCirc",
            "BlockName": "Pump",
            "BlockPosition": [
                -363.0,
                -434.0
            ],
            "FlippedH": false,
            "FlippedV": false,
            "GroupName": "defaultGroup",
            "ID": 816,
            "PortsIDIn": [
                817
            ],
            "PortsIDOut": [
                818
            ],
            "RotationN": 1,
            "trnsysID": 342
        },
        "Block-828": {
            ".__BlockDict__": true,
            "BlockDisplayName": "HxDHW",
            "BlockName": "ExternalHx",
            "ExternalHxPosition": [
                -593.0,
                -485.0
            ],
            "FlippedH": false,
            "FlippedV": false,
            "GroupName": "defaultGroup",
            "ID": 828,
            "PortsIDIn": [
                829,
                830
            ],
            "PortsIDOut": [
                831,
                832
            ],
            "RotationN": 0,
            "childIds": [
                346,
                347
            ],
            "trnsysID": 346
        },
        "Block-847": {
            ".__BlockDict__": true,
            "BlockDisplayName": "PuDHW",
            "BlockName": "Pump",
            "BlockPosition": [
                -645.0,
                -346.0
            ],
            "FlippedH": true,
            "FlippedV": false,
            "GroupName": "defaultGroup",
            "ID": 847,
            "PortsIDIn": [
                848
            ],
            "PortsIDOut": [
                849
            ],
            "RotationN": 0,
            "trnsysID": 353
        },
        "Block-868": {
            ".__BlockDict__": true,
            "BlockDisplayName": "DivDhwOut",
            "BlockName": "TVentil",
            "BlockPosition": [
                -751.0,
                -539.0
            ],
            "FlippedH": false,
            "FlippedV": true,
            "GroupName": "defaultGroup",
            "ID": 868,
            "IsTempering": false,
            "PortsIDIn": [
                869,
                870
            ],
            "PortsIDOut": [
                871
            ],
            "PositionForMassFlowSolver": 1.0,
            "RotationN": 0,
            "trnsysID": 360
        },
        "Block-881": {
            ".__BlockDict__": true,
            "BlockDisplayName": "DivDhw",
            "BlockName": "TVentil",
            "BlockPosition": [
                -750.0,
                -357.0
            ],
            "FlippedH": false,
            "FlippedV": false,
            "GroupName": "defaultGroup",
            "ID": 881,
            "IsTempering": false,
            "PortsIDIn": [
                882,
                883
            ],
            "PortsIDOut": [
                884
            ],
            "PositionForMassFlowSolver": 1.0,
            "RotationN": 0,
            "trnsysID": 364
        },
        "Connection-310": {
            ".__ConnectionDict__": true,
            "ConnCID": 150,
            "ConnDisplayName": "PiColIn",
            "ConnID": 310,
            "CornerPositions": [
                [
                    -1000.0,
                    -348.5
                ],
                [
                    -1000.0,
                    -350.0
                ]
            ],
            "FirstSegmentLabelPos": [
                -50.0,
                10.0
            ],
            "GroupName": "defaultGroup",
            "PortFromID": 6,
            "PortToID": 3,
            "SegmentPositions": [
                [
                    -1007.0,
                    -348.5,
                    -1000.0,
                    -348.5
                ],
                [
                    -1000.0,
                    -348.5,
                    -1000.0,
                    -350.0
                ],
                [
                    -1000.0,
                    -350.0,
                    -1102.0,
                    -350.0
                ]
            ],
            "isVirtualConn": false,
            "trnsysID": 172
        },
        "Connection-764": {
            ".__ConnectionDict__": true,
            "ConnCID": 261,
            "ConnDisplayName": "PiTesToCol",
            "ConnID": 764,
            "CornerPositions": [
                [
                    -852.0,
                    -348.5
                ],
                [
                    -852.0,
                    -345.0
                ]
            ],
            "FirstSegmentLabelPos": [
                30.0,
                10.0
            ],
            "GroupName": "defaultGroup",
            "PortFromID": 5,
            "PortToID": 760,
            "SegmentPositions": [
                [
                    -959.0,
                    -348.5,
                    -852.0,
                    -348.5
                ],
                [
                    -852.0,
                    -348.5,
                    -852.0,
                    -345.0
                ],
                [
                    -852.0,
                    -345.0,
                    -926.0,
                    -345.0
                ]
            ],
            "isVirtualConn": false,
            "trnsysID": 321
        },
        "Connection-767": {
            ".__ConnectionDict__": true,
            "ConnCID": 262,
            "ConnDisplayName": "PiColOut",
            "ConnID": 767,
            "CornerPositions": [
                [
                    -990.0,
                    -430.0
                ],
                [
                    -990.0,
                    -431.0
                ],
                [
                    -923.5,
                    -431.0
                ],
                [
                    -923.5,
                    -385.0
                ]
            ],
            "FirstSegmentLabelPos": [
                30.0,
                10.0
            ],
            "GroupName": "defaultGroup",
            "PortFromID": 2,
            "PortToID": 759,
            "SegmentPositions": [
                [
                    -1102.0,
                    -430.0,
                    -990.0,
                    -430.0
                ],
                [
                    -990.0,
                    -430.0,
                    -990.0,
                    -431.0
                ],
                [
                    -990.0,
                    -431.0,
                    -923.5,
                    -431.0
                ],
                [
                    -923.5,
                    -431.0,
                    -923.5,
                    -385.0
                ],
                [
                    -923.5,
                    -385.0,
                    -926.0,
                    -385.0
                ]
            ],
            "isVirtualConn": false,
            "trnsysID": 322
        },
        "Connection-825": {
            ".__ConnectionDict__": true,
            "ConnCID": 280,
            "ConnDisplayName": "PiPuCircOut",
            "ConnID": 825,
            "CornerPositions": [
                [
                    -386.0,
                    -394.0
                ],
                [
                    -386.0,
                    -371.0
                ],
                [
                    -379.0,
                    -371.0
                ],
                [
                    -379.0,
                    -370.0
                ]
            ],
            "FirstSegmentLabelPos": [
                20.0,
                0.0
            ],
            "GroupName": "defaultGroup",
            "PortFromID": 818,
            "PortToID": 21,
            "SegmentPositions": [
                [
                    -379.5,
                    -394.0,
                    -386.0,
                    -394.0
                ],
                [
                    -386.0,
                    -394.0,
                    -386.0,
                    -371.0
                ],
                [
                    -386.0,
                    -371.0,
                    -379.0,
                    -371.0
                ],
                [
                    -379.0,
                    -371.0,
                    -379.0,
                    -370.0
                ],
                [
                    -379.0,
                    -370.0,
                    -378.0,
                    -370.0
                ]
            ],
            "isVirtualConn": false,
            "trnsysID": 345
        },
        "Connection-850": {
            ".__ConnectionDict__": true,
            "ConnCID": 285,
            "ConnDisplayName": "PiDhwSecOut",
            "ConnID": 850,
            "CornerPositions": [
                [
                    -476.0,
                    -465.0
                ],
                [
                    -476.0,
                    -515.125
                ]
            ],
            "FirstSegmentLabelPos": [
                30.0,
                10.0
            ],
            "GroupName": "defaultGroup",
            "PortFromID": 830,
            "PortToID": 813,
            "SegmentPositions": [
                [
                    -485.0,
                    -465.0,
                    -476.0,
                    -465.0
                ],
                [
                    -476.0,
                    -465.0,
                    -476.0,
                    -515.125
                ],
                [
                    -476.0,
                    -515.125,
                    -407.0,
                    -515.125
                ]
            ],
            "isVirtualConn": false,
            "trnsysID": 354
        },
        "Connection-853": {
            ".__ConnectionDict__": true,
            "ConnCID": 286,
            "ConnDisplayName": "PiHxDhwSecIn",
            "ConnID": 853,
            "CornerPositions": [
                [
                    -445.5,
                    -327.875
                ],
                [
                    -445.5,
                    -402.0
                ]
            ],
            "FirstSegmentLabelPos": [
                -50.0,
                10.0
            ],
            "GroupName": "defaultGroup",
            "PortFromID": 19,
            "PortToID": 832,
            "SegmentPositions": [
                [
                    -406.0,
                    -327.875,
                    -445.5,
                    -327.875
                ],
                [
                    -445.5,
                    -327.875,
                    -445.5,
                    -402.0
                ],
                [
                    -445.5,
                    -402.0,
                    -485.0,
                    -402.0
                ]
            ],
            "isVirtualConn": false,
            "trnsysID": 355
        },
        "Connection-856": {
            ".__ConnectionDict__": true,
            "ConnCID": 287,
            "ConnDisplayName": "PiDhwDemand",
            "ConnID": 856,
            "CornerPositions": [
                [
                    -335.0,
                    -515.125
                ],
                [
                    -335.0,
                    -512.5
                ]
            ],
            "FirstSegmentLabelPos": [
                30.0,
                10.0
            ],
            "GroupName": "defaultGroup",
            "PortFromID": 814,
            "PortToID": 15,
            "SegmentPositions": [
                [
                    -351.0,
                    -515.125,
                    -335.0,
                    -515.125
                ],
                [
                    -335.0,
                    -515.125,
                    -335.0,
                    -512.5
                ],
                [
                    -335.0,
                    -512.5,
                    -226.0,
                    -512.5
                ]
            ],
            "isVirtualConn": false,
            "trnsysID": 356
        },
        "Connection-859": {
            ".__ConnectionDict__": true,
            "ConnCID": 288,
            "ConnDisplayName": "PiPuCircIn",
            "ConnID": 859,
            "CornerPositions": [
                [
                    -378.75,
                    -473.0
                ],
                [
                    -378.75,
                    -442.0
                ]
            ],
            "FirstSegmentLabelPos": [
                20.0,
                0.0
            ],
            "GroupName": "defaultGroup",
            "PortFromID": 815,
            "PortToID": 817,
            "SegmentPositions": [
                [
                    -379.0,
                    -473.0,
                    -378.75,
                    -473.0
                ],
                [
                    -378.75,
                    -473.0,
                    -378.75,
                    -442.0
                ],
                [
                    -379.5,
                    -442.0,
                    -378.75,
                    -442.0
                ]
            ],
            "isVirtualConn": false,
            "trnsysID": 357
        },
        "Connection-875": {
            ".__ConnectionDict__": true,
            "ConnCID": 292,
            "ConnDisplayName": "PiTesDhwOut",
            "ConnID": 875,
            "CornerPositions": [
                [
                    -791.0,
                    -489.0
                ],
                [
                    -791.0,
                    -516.7777777777778
                ]
            ],
            "FirstSegmentLabelPos": [
                20.0,
                0.0
            ],
            "GroupName": "defaultGroup",
            "PortFromID": 799,
            "PortToID": 869,
            "SegmentPositions": [
                [
                    -810.0,
                    -489.0,
                    -791.0,
                    -489.0
                ],
                [
                    -791.0,
                    -489.0,
                    -791.0,
                    -516.7777777777778
                ],
                [
                    -759.0,
                    -516.7777777777778,
                    -791.0,
                    -516.7777777777778
                ]
            ],
            "isVirtualConn": false,
            "trnsysID": 362
        },
        "Connection-878": {
            ".__ConnectionDict__": true,
            "ConnCID": 293,
            "ConnDisplayName": "PiCircOut",
            "ConnID": 878,
            "CornerPositions": [
                [
                    -774.5,
                    -481.0
                ],
                [
                    -774.5,
                    -481.0
                ]
            ],
            "FirstSegmentLabelPos": [
                20.0,
                0.0
            ],
            "GroupName": "defaultGroup",
            "PortFromID": 833,
            "PortToID": 870,
            "SegmentPositions": [
                [
                    -810.0,
                    -481.0,
                    -774.5,
                    -481.0
                ],
                [
                    -774.5,
                    -481.0,
                    -774.5,
                    -481.0
                ],
                [
                    -726.0,
                    -481.0,
                    -774.5,
                    -481.0
                ]
            ],
            "isVirtualConn": false,
            "trnsysID": 363
        },
        "Connection-888": {
            ".__ConnectionDict__": true,
            "ConnCID": 295,
            "ConnDisplayName": "PiTesDhwIn",
            "ConnID": 888,
            "CornerPositions": [
                [
                    -784.0,
                    -329.22222222222223
                ],
                [
                    -784.0,
                    -329.0
                ]
            ],
            "FirstSegmentLabelPos": [
                -60.0,
                0.0
            ],
            "GroupName": "defaultGroup",
            "PortFromID": 882,
            "PortToID": 800,
            "SegmentPositions": [
                [
                    -758.0,
                    -329.22222222222223,
                    -784.0,
                    -329.22222222222223
                ],
                [
                    -784.0,
                    -329.22222222222223,
                    -784.0,
                    -329.0
                ],
                [
                    -784.0,
                    -329.0,
                    -810.0,
                    -329.0
                ]
            ],
            "isVirtualConn": false,
            "trnsysID": 366
        },
        "Connection-895": {
            ".__ConnectionDict__": true,
            "ConnCID": 298,
            "ConnDisplayName": "PiDhwMains",
            "ConnID": 895,
            "CornerPositions": [
                [
                    -284.0,
                    -326.0
                ],
                [
                    -284.0,
                    -327.875
                ]
            ],
            "FirstSegmentLabelPos": [
                -50.0,
                10.0
            ],
            "GroupName": "defaultGroup",
            "PortFromID": 17,
            "PortToID": 20,
            "SegmentPositions": [
                [
                    -218.0,
                    -326.0,
                    -284.0,
                    -326.0
                ],
                [
                    -284.0,
                    -326.0,
                    -284.0,
                    -327.875
                ],
                [
                    -284.0,
                    -327.875,
                    -350.0,
                    -327.875
                ]
            ],
            "isVirtualConn": false,
            "trnsysID": 369
        },
        "Connection-898": {
            ".__ConnectionDict__": true,
            "ConnCID": 299,
            "ConnDisplayName": "PiHxDhwOut",
            "ConnID": 898,
            "CornerPositions": [
                [
                    -603.0,
                    -402.0
                ],
                [
                    -603.0,
                    -329.5
                ]
            ],
            "FirstSegmentLabelPos": [
                -60.0,
                0.0
            ],
            "GroupName": "defaultGroup",
            "PortFromID": 831,
            "PortToID": 848,
            "SegmentPositions": [
                [
                    -601.0,
                    -402.0,
                    -603.0,
                    -402.0
                ],
                [
                    -603.0,
                    -402.0,
                    -603.0,
                    -329.5
                ],
                [
                    -605.0,
                    -329.5,
                    -603.0,
                    -329.5
                ]
            ],
            "isVirtualConn": false,
            "trnsysID": 370
        },
        "Connection-901": {
            ".__ConnectionDict__": true,
            "ConnCID": 300,
            "ConnDisplayName": "PiPuDhwOut",
            "ConnID": 901,
            "CornerPositions": [
                [
                    -671.5,
                    -329.5
                ],
                [
                    -671.5,
                    -329.22222222222223
                ]
            ],
            "FirstSegmentLabelPos": [
                -60.0,
                0.0
            ],
            "GroupName": "defaultGroup",
            "PortFromID": 849,
            "PortToID": 884,
            "SegmentPositions": [
                [
                    -653.0,
                    -329.5,
                    -671.5,
                    -329.5
                ],
                [
                    -671.5,
                    -329.5,
                    -671.5,
                    -329.22222222222223
                ],
                [
                    -692.0,
                    -329.22222222222223,
                    -671.5,
                    -329.22222222222223
                ]
            ],
            "isVirtualConn": false,
            "trnsysID": 371
        },
        "Connection-904": {
            ".__ConnectionDict__": true,
            "ConnCID": 301,
            "ConnDisplayName": "PiHxDhwIn",
            "ConnID": 904,
            "CornerPositions": [
                [
                    -655.0,
                    -516.7777777777778
                ],
                [
                    -655.0,
                    -465.0
                ]
            ],
            "FirstSegmentLabelPos": [
                20.0,
                0.0
            ],
            "GroupName": "defaultGroup",
            "PortFromID": 871,
            "PortToID": 829,
            "SegmentPositions": [
                [
                    -693.0,
                    -516.7777777777778,
                    -655.0,
                    -516.7777777777778
                ],
                [
                    -655.0,
                    -516.7777777777778,
                    -655.0,
                    -465.0
                ],
                [
                    -655.0,
                    -465.0,
                    -601.0,
                    -465.0
                ]
            ],
            "isVirtualConn": false,
            "trnsysID": 372
        },
        "Connection-907": {
            ".__ConnectionDict__": true,
            "ConnCID": 302,
            "ConnDisplayName": "PiCircIn",
            "ConnID": 907,
            "CornerPositions": [
                [
                    -767.5,
                    -365.0
                ],
                [
                    -767.5,
                    -433.0
                ]
            ],
            "FirstSegmentLabelPos": [
                20.0,
                0.0
            ],
            "GroupName": "defaultGroup",
            "PortFromID": 883,
            "PortToID": 834,
            "SegmentPositions": [
                [
                    -725.0,
                    -365.0,
                    -767.5,
                    -365.0
                ],
                [
                    -767.5,
                    -365.0,
                    -767.5,
                    -433.0
                ],
                [
                    -767.5,
                    -433.0,
                    -810.0,
                    -433.0
                ]
            ],
            "isVirtualConn": false,
            "trnsysID": 373
        },
        "GraphicalItem-777": {
            ".__BlockDict__": true,
            "BlockName": "GraphicalItem",
            "BlockPosition": [
                -886.0,
                -497.0
            ],
            "FlippedH": false,
            "FlippedV": false,
            "ID": 777,
            "ImageSource": "C:/Daten/spfPackages/GIT/TrnsysGUI/trnsysGUI/images/ElectricRod.svg",
            "RotationN": 0,
            "Size": [
                68.0,
                68.0
            ]
        },
        "IDs": {
            "GlobalId": 911,
            "__idDct__": true,
            "globalConnID": 304,
            "trnsysID": 375
        },
        "Strings": {
            "DiagramName": "DHWSolar+TesMFH",
            "__nameDct__": true
        }
    }
}